{
  "page": 4,
  "value": [
    {
      "path": "_news/2022-03-02-deep-learning-diagnoses-ai-detects-covid-19-from-smartwatch-sensors.md",
      "title": "Deep-learning diagnoses: AI detects COVID-19 from smartwatch sensors",
      "excerpt": "Combining questions about a person's health with data from smartwatch sensors, a new app developed using research at Princeton University can predict within minutes whether someone is infected with COVID-19.",
      "sourceUrl": null,
      "webUrl": "https://techxplore.com/news/2022-03-deep-learning-ai-covid-smartwatch-sensors.html",
      "originalUrl": "https://techxplore.com/news/2022-03-deep-learning-ai-covid-smartwatch-sensors.html",
      "featuredContent": null,
      "highlight": null,
      "heat": 89,
      "tags": null,
      "images": [
        {
          "url": "https://scx2.b-cdn.net/gfx/news/hires/2022/deep-learning-diagnose.jpg",
          "width": 1536,
          "height": 864,
          "title": null,
          "attribution": null,
          "isCached": true
        }
      ],
      "content": "\r\n",
      "type": "article",
      "ampWebUrl": "https://techxplore.com/news/2022-03-deep-learning-ai-covid-smartwatch-sensors.amp",
      "cdnAmpWebUrl": "https://techxplore-com.cdn.ampproject.org/c/s/techxplore.com/news/2022-03-deep-learning-ai-covid-smartwatch-sensors.amp",
      "publishedDateTime": "2022-03-01T08:10:00-08:00",
      "updatedDateTime": null,
      "provider": {
        "name": "techxplore.com",
        "domain": "techxplore.com",
        "images": null,
        "publishers": null,
        "authors": null
      },
      "locale": "en-us",
      "categories": [
        "news"
      ],
      "topics": [
        "Machine Learning",
        "AI"
      ]
    },
    {
      "path": "_news/2022-03-02-injecting-fairness-into-machine-learning-models.md",
      "title": "Injecting fairness into machine-learning models",
      "excerpt": "If a machine-learning model is trained using an unbalanced dataset, such as one that contains far more images of people with lighter skin than people with darker skin, there is serious risk the model's predictions will be unfair when it is deployed in the real world.",
      "sourceUrl": null,
      "webUrl": "https://techxplore.com/news/2022-03-fairness-machine-learning.html",
      "originalUrl": "https://techxplore.com/news/2022-03-fairness-machine-learning.html",
      "featuredContent": null,
      "highlight": null,
      "heat": 109,
      "tags": null,
      "images": [
        {
          "url": "https://scx2.b-cdn.net/gfx/news/2022/injecting-fairness-int.jpg",
          "width": 900,
          "height": 600,
          "title": null,
          "attribution": null,
          "isCached": true
        }
      ],
      "content": "\r\n",
      "type": "article",
      "ampWebUrl": "https://techxplore.com/news/2022-03-fairness-machine-learning.amp",
      "cdnAmpWebUrl": "https://techxplore-com.cdn.ampproject.org/c/s/techxplore.com/news/2022-03-fairness-machine-learning.amp",
      "publishedDateTime": "2022-03-01T08:10:00-08:00",
      "updatedDateTime": null,
      "provider": {
        "name": "techxplore.com",
        "domain": "techxplore.com",
        "images": null,
        "publishers": null,
        "authors": null
      },
      "locale": "en-us",
      "categories": [
        "news"
      ],
      "topics": [
        "Machine Learning",
        "AI"
      ]
    },
    {
      "path": "_news/2022-03-02-ai-robotics-and-ethics-harnessing-the-power-of-intelligent-machines-to-benefit-humans.md",
      "title": "AI, Robotics And Ethics: Harnessing The Power Of Intelligent Machines To Benefit Humans",
      "excerpt": "The importance of ethics in artificial intelligence stems from the power of what can be accomplished with AI, especially when combined with machines: self-driving cars, robots co-working with humans in factories,",
      "sourceUrl": null,
      "webUrl": "https://www.forbes.com/sites/windriver/2022/03/01/ai-robotics-and-ethics-harnessing-the-power-of-intelligent-machines-to-benefit-humans/",
      "originalUrl": "https://www.forbes.com/sites/windriver/2022/03/01/ai-robotics-and-ethics-harnessing-the-power-of-intelligent-machines-to-benefit-humans/",
      "featuredContent": null,
      "highlight": null,
      "heat": 138,
      "tags": null,
      "images": [
        {
          "url": "https://imageio.forbes.com/specials-images/imageserve/621e4c1c73b90ce7ffd5d84a/0x0.jpg?format=jpg&width=1200&fit=bounds",
          "width": 1200,
          "height": 645,
          "title": null,
          "attribution": null,
          "isCached": true
        }
      ],
      "content": "\r\n",
      "type": "article",
      "ampWebUrl": "https://www.forbes.com/sites/windriver/2022/03/01/ai-robotics-and-ethics-harnessing-the-power-of-intelligent-machines-to-benefit-humans/amp/",
      "cdnAmpWebUrl": "https://www-forbes-com.cdn.ampproject.org/c/s/www.forbes.com/sites/windriver/2022/03/01/ai-robotics-and-ethics-harnessing-the-power-of-intelligent-machines-to-benefit-humans/amp/",
      "publishedDateTime": "2022-03-01T08:02:00-08:00",
      "updatedDateTime": null,
      "provider": {
        "name": "Forbes",
        "domain": "forbes.com",
        "images": [
          {
            "url": "https://everyday-cc.github.io/ai/assets/images/organizations/forbes.com-50x50.jpg",
            "width": 50,
            "height": 50,
            "title": null,
            "attribution": null,
            "isCached": false
          }
        ],
        "publishers": null,
        "authors": null
      },
      "locale": "en-us",
      "categories": [
        "news"
      ],
      "topics": [
        "AI Ethics",
        "AI",
        "AI in Robotics"
      ]
    },
    {
      "path": "_news/2022-03-01-ai-deciding-how-to-distribute-harm-breeds-dicey-ai-ethics-dilemma-markedly-so-for-nascent-ai-based-self-driving-cars.md",
      "title": "AI Deciding How To Distribute Harm Breeds Dicey AI Ethics Dilemma, Markedly So For Nascent AI-Based Self-Driving Cars",
      "excerpt": "AI systems are having to ascertain how to distribute harm, a decidedly Ethical AI issue, including for the case of AI self-driving cars.",
      "sourceUrl": null,
      "webUrl": "https://www.forbes.com/sites/lanceeliot/2022/03/01/ai-deciding-how-to-distribute-harm-breeds-dicey-ai-ethics-dilemma-markedly-so-for-nascent-ai-based-self-driving-cars/",
      "originalUrl": "https://www.forbes.com/sites/lanceeliot/2022/03/01/ai-deciding-how-to-distribute-harm-breeds-dicey-ai-ethics-dilemma-markedly-so-for-nascent-ai-based-self-driving-cars/",
      "featuredContent": null,
      "highlight": null,
      "heat": 83,
      "tags": null,
      "images": [
        {
          "url": "https://imageio.forbes.com/specials-images/imageserve/62184c65dbd6bd0c97949c9c/0x0.jpg?format=jpg&crop=5676,3194,x0,y188,safe&fit=crop",
          "width": 5676,
          "height": 3194,
          "title": null,
          "attribution": null,
          "isCached": true
        }
      ],
      "content": "\r\n",
      "type": "article",
      "ampWebUrl": "https://www.forbes.com/sites/lanceeliot/2022/03/01/ai-deciding-how-to-distribute-harm-breeds-dicey-ai-ethics-dilemma-markedly-so-for-nascent-ai-based-self-driving-cars/amp/",
      "cdnAmpWebUrl": "https://www-forbes-com.cdn.ampproject.org/c/s/www.forbes.com/sites/lanceeliot/2022/03/01/ai-deciding-how-to-distribute-harm-breeds-dicey-ai-ethics-dilemma-markedly-so-for-nascent-ai-based-self-driving-cars/amp/",
      "publishedDateTime": "2022-03-01T07:30:00-08:00",
      "updatedDateTime": null,
      "provider": {
        "name": "Forbes",
        "domain": "forbes.com",
        "images": [
          {
            "url": "https://everyday-cc.github.io/ai/assets/images/organizations/forbes.com-50x50.jpg",
            "width": 50,
            "height": 50,
            "title": null,
            "attribution": null,
            "isCached": false
          }
        ],
        "publishers": null,
        "authors": null
      },
      "locale": "en-us",
      "categories": [
        "news"
      ],
      "topics": [
        "AI",
        "AI Ethics",
        "AI in Autos"
      ]
    },
    {
      "path": "_news/2022-03-01-zero-systems-gets-12m-series-a-to-bring-automation-to-professional-services.md",
      "title": "Zero Systems gets $12M Series A to bring automation to professional services",
      "excerpt": "Zero Systems launched seven years ago with an idea to bring automation to professional services like law firms. They wanted to focus on speeding up manual tasks, rather than moving large volumes of information,",
      "sourceUrl": null,
      "webUrl": "https://techcrunch.com/2022/03/01/zero-systems-gets-12m-series-a-to-bring-automation-to-professional-services/",
      "originalUrl": "https://techcrunch.com/2022/03/01/zero-systems-gets-12m-series-a-to-bring-automation-to-professional-services/",
      "featuredContent": null,
      "highlight": null,
      "heat": 71,
      "tags": null,
      "images": [
        {
          "url": "https://techcrunch.com/wp-content/uploads/2022/03/GettyImages-1153689483.jpg?w=1024",
          "width": 1024,
          "height": 681,
          "title": null,
          "attribution": null,
          "isCached": true
        }
      ],
      "content": "\r\n",
      "type": "article",
      "ampWebUrl": "https://techcrunch.com/2022/03/01/zero-systems-gets-12m-series-a-to-bring-automation-to-professional-services/amp/",
      "cdnAmpWebUrl": "https://techcrunch-com.cdn.ampproject.org/c/s/techcrunch.com/2022/03/01/zero-systems-gets-12m-series-a-to-bring-automation-to-professional-services/amp/",
      "publishedDateTime": "2022-03-01T07:18:00-08:00",
      "updatedDateTime": null,
      "provider": {
        "name": "TechCrunch",
        "domain": "techcrunch.com",
        "images": [
          {
            "url": "https://everyday-cc.github.io/ai/assets/images/organizations/techcrunch.com-50x50.jpg",
            "width": 50,
            "height": 50,
            "title": null,
            "attribution": null,
            "isCached": false
          }
        ],
        "publishers": null,
        "authors": null
      },
      "locale": "en-us",
      "categories": [
        "news"
      ],
      "topics": [
        "AI in Finance",
        "AI"
      ]
    },
    {
      "path": "_news/2022-03-01-7-must-read-books-about-artificial-intelligence.md",
      "title": "7 Must-Read Books About Artificial Intelligence",
      "excerpt": "In late 2019, we published “7 Classic Books To Deepen Your Understanding Of Artificial Intelligence.” It’s time to run it back. Here are 7 more thought-provoking books that explore the technology, business,",
      "sourceUrl": null,
      "webUrl": "https://www.forbes.com/sites/robtoews/2022/03/01/7-must-read-books-about-artificial-intelligence/",
      "originalUrl": "https://www.forbes.com/sites/robtoews/2022/03/01/7-must-read-books-about-artificial-intelligence/",
      "featuredContent": null,
      "highlight": null,
      "heat": 87,
      "tags": null,
      "images": [
        {
          "url": "https://imageio.forbes.com/specials-images/imageserve/621c5e573cd0ac3fb2b884a3/0x0.jpg?format=jpg&crop=900,507,x0,y77,safe&fit=crop",
          "width": 900,
          "height": 507,
          "title": null,
          "attribution": null,
          "isCached": true
        }
      ],
      "content": "\r\n",
      "type": "article",
      "ampWebUrl": "https://www.forbes.com/sites/robtoews/2022/03/01/7-must-read-books-about-artificial-intelligence/amp/",
      "cdnAmpWebUrl": "https://www-forbes-com.cdn.ampproject.org/c/s/www.forbes.com/sites/robtoews/2022/03/01/7-must-read-books-about-artificial-intelligence/amp/",
      "publishedDateTime": "2022-03-01T06:45:00-08:00",
      "updatedDateTime": null,
      "provider": {
        "name": "Forbes",
        "domain": "forbes.com",
        "images": [
          {
            "url": "https://everyday-cc.github.io/ai/assets/images/organizations/forbes.com-50x50.jpg",
            "width": 50,
            "height": 50,
            "title": null,
            "attribution": null,
            "isCached": false
          }
        ],
        "publishers": null,
        "authors": null
      },
      "locale": "en-us",
      "categories": [
        "news"
      ],
      "topics": [
        "AI"
      ]
    },
    {
      "path": "_news/2022-03-01-how-to-become-an-ai-driven-company-today-part-1.md",
      "title": "How To Become An AI-Driven Company Today (Part 1)",
      "excerpt": "Similarly, becoming an AI-driven company is a top strategic endeavor. It's a cultural change. It's a people challenge. And it requires changes in many fundamentals of your organization. Here are my perspectives and learnings on this from the field.",
      "sourceUrl": null,
      "webUrl": "https://www.forbes.com/sites/forbestechcouncil/2022/03/01/how-to-become-an-ai-driven-company-today-part-1/",
      "originalUrl": "https://www.forbes.com/sites/forbestechcouncil/2022/03/01/how-to-become-an-ai-driven-company-today-part-1/",
      "featuredContent": null,
      "highlight": null,
      "heat": 87,
      "tags": null,
      "images": [
        {
          "url": "https://imageio.forbes.com/specials-images/imageserve/60aebd253bb898555bf94d92/0x0.jpg?format=jpg&width=1200&fit=bounds",
          "width": 1200,
          "height": 800,
          "title": null,
          "attribution": null,
          "isCached": true
        }
      ],
      "content": "\r\n",
      "type": "article",
      "ampWebUrl": "https://www.forbes.com/sites/forbestechcouncil/2022/03/01/how-to-become-an-ai-driven-company-today-part-1/amp/",
      "cdnAmpWebUrl": "https://www-forbes-com.cdn.ampproject.org/c/s/www.forbes.com/sites/forbestechcouncil/2022/03/01/how-to-become-an-ai-driven-company-today-part-1/amp/",
      "publishedDateTime": "2022-03-01T05:45:00-08:00",
      "updatedDateTime": null,
      "provider": {
        "name": "Forbes",
        "domain": "forbes.com",
        "images": [
          {
            "url": "https://everyday-cc.github.io/ai/assets/images/organizations/forbes.com-50x50.jpg",
            "width": 50,
            "height": 50,
            "title": null,
            "attribution": null,
            "isCached": false
          }
        ],
        "publishers": null,
        "authors": null
      },
      "locale": "en-us",
      "categories": [
        "news"
      ],
      "topics": [
        "AI"
      ]
    },
    {
      "path": "_news/2022-03-01-california-greenlights-cruise-waymo-autonomous-vehicle-service.md",
      "title": "California Greenlights Cruise, Waymo Autonomous Vehicle Service",
      "excerpt": "Autonomous vehicle makers General Motors and Alphabet Inc. can now collect fares from passengers of self-driving cars in California. The state's Public Utilities Commission (CPUC) this week gave the green light for GM's Cruise and Alphabet's Waymo to charge for rides in autonomous vehicles—with safety drivers present.",
      "sourceUrl": null,
      "webUrl": "https://www.pcmag.com/news/california-greenlights-cruise-waymo-autonomous-vehicle-service",
      "originalUrl": "https://in.pcmag.com/cars-auto/148155/california-greenlights-cruise-waymo-autonomous-vehicle-service",
      "featuredContent": null,
      "highlight": null,
      "heat": 199,
      "tags": null,
      "images": [
        {
          "url": "https://i.pcmag.com/imagery/articles/01ANFiVScbhSTtWFUMUy2or-1.fit_lim.size_1200x630.v1646134551.jpg",
          "width": 1120,
          "height": 630,
          "title": null,
          "attribution": null,
          "isCached": true
        }
      ],
      "content": "\r\n",
      "type": "article",
      "ampWebUrl": "https://www.pcmag.com/news/california-greenlights-cruise-waymo-autonomous-vehicle-service?amp=true",
      "cdnAmpWebUrl": "https://www-pcmag-com.cdn.ampproject.org/c/s/www.pcmag.com/news/california-greenlights-cruise-waymo-autonomous-vehicle-service?amp=true",
      "publishedDateTime": "2022-03-01T05:30:00-08:00",
      "updatedDateTime": null,
      "provider": {
        "name": "PC Magazine",
        "domain": "pcmag.com",
        "images": [
          {
            "url": "/assets/images/organizations/pcmag.com-50x50.jpg",
            "width": 50,
            "height": 50,
            "title": null,
            "attribution": null,
            "isCached": false
          }
        ],
        "publishers": null,
        "authors": null
      },
      "locale": "en-us",
      "categories": [
        "news"
      ],
      "topics": [
        "AI",
        "AI in Autos"
      ]
    },
    {
      "path": "_news/2022-03-01-chinas-algorithm-law-takes-effect-to-curb-big-techs-sway-in-public-opinion.md",
      "title": "China’s algorithm law takes effect to curb Big Tech’s sway in public opinion",
      "excerpt": "A new regulation in China designed to rein in the use of recommendation algorithms in apps went into effect on Tuesday, representing Beijing’s latest effort to curb the influence of Big Tech ... to the CAC post. Under the new rules, tech companies ...",
      "sourceUrl": null,
      "webUrl": "https://www.scmp.com/tech/policy/article/3168816/chinas-algorithm-law-takes-effect-curb-big-techs-sway-public-opinion",
      "originalUrl": "https://www.scmp.com/tech/policy/article/3168816/chinas-algorithm-law-takes-effect-curb-big-techs-sway-public-opinion",
      "featuredContent": null,
      "highlight": null,
      "heat": 169,
      "tags": null,
      "images": [
        {
          "url": "https://cdn.i-scmp.com/sites/default/files/styles/og_image_scmp_generic/public/d8/images/canvas/2022/03/01/b3b85a22-5186-438a-a453-ce7427e4037d_1c027c76.jpg?itok=aiLBSdXN&v=1646128154",
          "width": 1200,
          "height": 630,
          "title": null,
          "attribution": null,
          "isCached": true
        }
      ],
      "content": "\r\n",
      "type": "article",
      "ampWebUrl": "https://amp.scmp.com/tech/policy/article/3168816/chinas-algorithm-law-takes-effect-curb-big-techs-sway-public-opinion",
      "cdnAmpWebUrl": "https://amp-scmp-com.cdn.ampproject.org/c/s/amp.scmp.com/tech/policy/article/3168816/chinas-algorithm-law-takes-effect-curb-big-techs-sway-public-opinion",
      "publishedDateTime": "2022-03-01T04:29:00-08:00",
      "updatedDateTime": null,
      "provider": {
        "name": "South China Morning Post",
        "domain": "scmp.com",
        "images": [
          {
            "url": "/assets/images/organizations/scmp.com-50x50.jpg",
            "width": 50,
            "height": 50,
            "title": null,
            "attribution": null,
            "isCached": false
          }
        ],
        "publishers": null,
        "authors": null
      },
      "locale": "en-us",
      "categories": [
        "news"
      ],
      "topics": [
        "AI"
      ]
    },
    {
      "path": "_news/2022-03-01-16-tech-experts-share-advice-for-companies-considering-an-ai-plan.md",
      "title": "16 Tech Experts Share Advice For Companies Considering An AI Plan",
      "excerpt": "Determining if AI will be a helpful tool for your organization and, if so, how and where to deploy it takes careful planning, groundwork and teamwide buy-in.",
      "sourceUrl": null,
      "webUrl": "https://www.forbes.com/sites/forbestechcouncil/2022/03/01/16-tech-experts-share-advice-for-companies-considering-an-ai-plan/",
      "originalUrl": "https://www.forbes.com/sites/forbestechcouncil/2022/03/01/16-tech-experts-share-advice-for-companies-considering-an-ai-plan/",
      "featuredContent": null,
      "highlight": null,
      "heat": 87,
      "tags": null,
      "images": [
        {
          "url": "https://imageio.forbes.com/specials-images/imageserve/611197e7a1fc8d3b4e5a536a/0x0.jpg?format=jpg&width=1200&fit=bounds",
          "width": 1200,
          "height": 652,
          "title": null,
          "attribution": null,
          "isCached": true
        }
      ],
      "content": "\r\n",
      "type": "article",
      "ampWebUrl": "https://www.forbes.com/sites/forbestechcouncil/2022/03/01/16-tech-experts-share-advice-for-companies-considering-an-ai-plan/amp/",
      "cdnAmpWebUrl": "https://www-forbes-com.cdn.ampproject.org/c/s/www.forbes.com/sites/forbestechcouncil/2022/03/01/16-tech-experts-share-advice-for-companies-considering-an-ai-plan/amp/",
      "publishedDateTime": "2022-03-01T04:15:00-08:00",
      "updatedDateTime": null,
      "provider": {
        "name": "Forbes",
        "domain": "forbes.com",
        "images": [
          {
            "url": "https://everyday-cc.github.io/ai/assets/images/organizations/forbes.com-50x50.jpg",
            "width": 50,
            "height": 50,
            "title": null,
            "attribution": null,
            "isCached": false
          }
        ],
        "publishers": null,
        "authors": null
      },
      "locale": "en-us",
      "categories": [
        "news"
      ],
      "topics": [
        "AI"
      ]
    },
    {
      "path": "_news/2022-03-01-ai-in-healthcare-market-is-projected-to-reach-1944-billion-by-2030.md",
      "title": "AI in Healthcare Market is projected to reach $194.4 billion by 2030",
      "excerpt": "COVID-19 is an infectious disease caused by the most recently discovered novel corona virus. Largely unknown before the outbreak began in Wuhan (China) in December 2019, COVID-19 has moved from a regional crisis to a global pandemic in just a matter of a ...",
      "sourceUrl": null,
      "webUrl": "https://www.digitaljournal.com/pr/ai-in-healthcare-market-is-projected-to-reach-194-4-billion-by-2030",
      "originalUrl": "https://www.digitaljournal.com/pr/ai-in-healthcare-market-is-projected-to-reach-194-4-billion-by-2030",
      "featuredContent": null,
      "highlight": null,
      "heat": 104,
      "tags": null,
      "images": [
        {
          "url": "https://www.digitaljournal.com/wp-content/uploads/2022/02/BBB-10-600x337.png",
          "width": 600,
          "height": 337,
          "title": null,
          "attribution": null,
          "isCached": true
        }
      ],
      "content": "\r\n",
      "type": "article",
      "ampWebUrl": null,
      "cdnAmpWebUrl": null,
      "publishedDateTime": "2022-03-01T03:51:00-08:00",
      "updatedDateTime": null,
      "provider": {
        "name": "Digital Journal",
        "domain": "digitaljournal.com",
        "images": null,
        "publishers": null,
        "authors": null
      },
      "locale": "en-us",
      "categories": [
        "news"
      ],
      "topics": [
        "AI",
        "AI in Healthcare"
      ]
    },
    {
      "path": "_news/2022-03-01-buffett-backed-byd-to-use-baidu-apollos-autonomous-driving-technology-in-its-evs-as-it-raises-its-game-against-tesla-domestic-rivals.md",
      "title": "Buffett-backed BYD to use Baidu Apollo’s autonomous driving technology in its EVs as it raises its game against Tesla, domestic rivals",
      "excerpt": "It will be an important step for Beijing-based Baidu too, as it strives to commercialise its Apollo self-driving technologies after nearly five year of development. “BYD’s EVs have a good ...",
      "sourceUrl": null,
      "webUrl": "https://www.scmp.com/business/china-business/article/3168807/buffett-backed-byd-use-baidu-apollos-autonomous-driving",
      "originalUrl": "https://www.scmp.com/business/china-business/article/3168807/buffett-backed-byd-use-baidu-apollos-autonomous-driving",
      "featuredContent": null,
      "highlight": null,
      "heat": 72,
      "tags": null,
      "images": [
        {
          "url": "https://cdn.i-scmp.com/sites/default/files/styles/og_image_scmp_generic/public/d8/images/canvas/2022/03/01/0b981023-b94c-4324-be7a-50218aaf4a76_75ac7235.jpg?itok=El5opAGi&v=1646126110",
          "width": 1200,
          "height": 630,
          "title": null,
          "attribution": null,
          "isCached": true
        }
      ],
      "content": "\r\n",
      "type": "article",
      "ampWebUrl": "https://amp.scmp.com/business/china-business/article/3168807/buffett-backed-byd-use-baidu-apollos-autonomous-driving",
      "cdnAmpWebUrl": "https://amp-scmp-com.cdn.ampproject.org/c/s/amp.scmp.com/business/china-business/article/3168807/buffett-backed-byd-use-baidu-apollos-autonomous-driving",
      "publishedDateTime": "2022-03-01T03:33:00-08:00",
      "updatedDateTime": null,
      "provider": {
        "name": "South China Morning Post",
        "domain": "scmp.com",
        "images": [
          {
            "url": "https://everyday-cc.github.io/ai/assets/images/organizations/scmp.com-50x50.jpg",
            "width": 50,
            "height": 50,
            "title": null,
            "attribution": null,
            "isCached": false
          }
        ],
        "publishers": null,
        "authors": null
      },
      "locale": "en-us",
      "categories": [
        "news"
      ],
      "topics": [
        "AI in Autos",
        "AI"
      ]
    },
    {
      "path": "_news/2022-03-01-why-tech-marketing-leaders-are-racing-to-sponsor-formula-1.md",
      "title": "Why Tech Marketing Leaders Are Racing To Sponsor Formula 1",
      "excerpt": "With the rising popularity of Formula 1, technology companies are expanding their sponsorships and seeing amazing returns on their investments.",
      "sourceUrl": null,
      "webUrl": "https://www.forbes.com/sites/johnellett/2022/03/01/why-tech-marketing-leaders-are-racing-to-sponsor-formula-1/",
      "originalUrl": "https://www.forbes.com/sites/johnellett/2022/03/01/why-tech-marketing-leaders-are-racing-to-sponsor-formula-1/",
      "featuredContent": null,
      "highlight": null,
      "heat": 111,
      "tags": null,
      "images": [
        {
          "url": "https://imageio.forbes.com/specials-images/imageserve/621524e4c9ebfd7631a869a8/0x0.jpg?format=jpg&width=1200&fit=bounds",
          "width": 1200,
          "height": 800,
          "title": null,
          "attribution": null,
          "isCached": true
        }
      ],
      "content": "\r\n",
      "type": "article",
      "ampWebUrl": "https://www.forbes.com/sites/johnellett/2022/03/01/why-tech-marketing-leaders-are-racing-to-sponsor-formula-1/amp/",
      "cdnAmpWebUrl": "https://www-forbes-com.cdn.ampproject.org/c/s/www.forbes.com/sites/johnellett/2022/03/01/why-tech-marketing-leaders-are-racing-to-sponsor-formula-1/amp/",
      "publishedDateTime": "2022-03-01T02:00:00-08:00",
      "updatedDateTime": null,
      "provider": {
        "name": "Forbes",
        "domain": "forbes.com",
        "images": [
          {
            "url": "https://everyday-cc.github.io/ai/assets/images/organizations/forbes.com-50x50.jpg",
            "width": 50,
            "height": 50,
            "title": null,
            "attribution": null,
            "isCached": false
          }
        ],
        "publishers": null,
        "authors": null
      },
      "locale": "en-us",
      "categories": [
        "news"
      ],
      "topics": [
        "AWS AI",
        "AI",
        "AI in Marketing"
      ]
    },
    {
      "path": "_news/2022-03-01-fintech-startup-snapmint-raises-9-mn-to-launch-innovative-bnpl-products.md",
      "title": "Fintech Startup Snapmint Raises $9 Mn To Launch Innovative BNPL Products",
      "excerpt": "Besides, Snapmint plans to expand its network of merchants and power the purchases of more than 450 Mn consumers in India",
      "sourceUrl": null,
      "webUrl": "https://inc42.com/buzz/fintech-startup-snapmint-raises-9-mn-to-launch-innovative-bnpl-products/",
      "originalUrl": "https://inc42.com/buzz/fintech-startup-snapmint-raises-9-mn-to-launch-innovative-bnpl-products/",
      "featuredContent": null,
      "highlight": null,
      "heat": 78,
      "tags": null,
      "images": [
        {
          "url": "https://inc42.com/wp-content/uploads/2022/03/Snapmint-social.png",
          "width": 1200,
          "height": 628,
          "title": null,
          "attribution": null,
          "isCached": true
        }
      ],
      "content": "\r\n",
      "type": "article",
      "ampWebUrl": "https://inc42.com/buzz/fintech-startup-snapmint-raises-9-mn-to-launch-innovative-bnpl-products/amp/",
      "cdnAmpWebUrl": "https://inc42-com.cdn.ampproject.org/c/s/inc42.com/buzz/fintech-startup-snapmint-raises-9-mn-to-launch-innovative-bnpl-products/amp/",
      "publishedDateTime": "2022-03-01T01:15:00-08:00",
      "updatedDateTime": null,
      "provider": {
        "name": "inc42.com",
        "domain": "inc42.com",
        "images": null,
        "publishers": null,
        "authors": null
      },
      "locale": "en-us",
      "categories": [
        "news"
      ],
      "topics": [
        "AI in Finance",
        "AI"
      ]
    },
    {
      "path": "_news/2022-03-01-baidu-beats-quarterly-revenue-estimates.md",
      "title": "Baidu beats quarterly revenue estimates",
      "excerpt": "Chinese search engine giant Baidu Inc reported quarterly revenue above Wall Street estimates on Tuesday, powered by high demand for its cloud and self-driving taxi services. March 1 (Reuters ...",
      "sourceUrl": null,
      "webUrl": "https://www.nasdaq.com/articles/baidu-beats-quarterly-revenue-estimates",
      "originalUrl": "https://www.nasdaq.com/articles/baidu-beats-quarterly-revenue-estimates",
      "featuredContent": null,
      "highlight": null,
      "heat": 149,
      "tags": null,
      "images": null,
      "content": "\r\n",
      "type": "article",
      "ampWebUrl": "https://www.nasdaq.com/articles/baidu-beats-quarterly-revenue-estimates?amp",
      "cdnAmpWebUrl": "https://www-nasdaq-com.cdn.ampproject.org/c/s/www.nasdaq.com/articles/baidu-beats-quarterly-revenue-estimates?amp",
      "publishedDateTime": "2022-03-01T00:53:00-08:00",
      "updatedDateTime": null,
      "provider": {
        "name": "Nasdaq",
        "domain": "nasdaq.com",
        "images": null,
        "publishers": null,
        "authors": null
      },
      "locale": "en-us",
      "categories": [
        "news"
      ],
      "topics": [
        "AI in Autos",
        "AI"
      ]
    },
    {
      "path": "_news/2022-03-01-cyber-security-in-robotics-market-2022-key-players-end-user-demand-and-consumption-by-2029.md",
      "title": "Cyber Security in Robotics Market 2022 Key Players, End User, Demand and Consumption by 2029",
      "excerpt": "AM 'A new market research report by Future Market Insights on cyber security in robotics market includes industry analysis 201",
      "sourceUrl": null,
      "webUrl": "https://menafn.com/1103780722/Cyber-Security-in-Robotics-Market-2022-Key-Players-End-User-Demand-and-Consumption-by-2029",
      "originalUrl": "https://menafn.com/1103780722/Cyber-Security-in-Robotics-Market-2022-Key-Players-End-User-Demand-and-Consumption-by-2029",
      "featuredContent": null,
      "highlight": null,
      "heat": 70,
      "tags": null,
      "images": [
        {
          "url": "https://menafn.com/Updates/index/HTML_Images/NewsEn_MoreStories_img_1.jpg?55562",
          "width": 444,
          "height": 250,
          "title": null,
          "attribution": null,
          "isCached": true
        }
      ],
      "content": "\r\n",
      "type": "article",
      "ampWebUrl": null,
      "cdnAmpWebUrl": null,
      "publishedDateTime": "2022-03-01T00:46:00-08:00",
      "updatedDateTime": null,
      "provider": {
        "name": "Middle East North Africa Financial Network",
        "domain": "menafn.com",
        "images": null,
        "publishers": null,
        "authors": null
      },
      "locale": "en-us",
      "categories": [
        "news"
      ],
      "topics": [
        "AI in Robotics",
        "AI",
        "AI in Security"
      ]
    },
    {
      "path": "_news/2022-03-01-att-and-ibm-co-develop-ai-5g-and-hybrid-cloud-simulation-center.md",
      "title": "AT&T and IBM co-develop AI, 5G, and hybrid cloud simulation center",
      "excerpt": "AT&T and IBM have partnered to offer simulated environments for enterprises to test out AT&T's 5G network capabilities alongside IBM's artificial intelligence (AI) and hybrid cloud technologies. The firms noted businesses across all industries,",
      "sourceUrl": null,
      "webUrl": "https://www.itpro.co.uk/mobile/5g/364038/att-and-ibm-co-develop-ai-5g-and-hybrid-cloud-simulation-center",
      "originalUrl": "https://www.itpro.co.uk/mobile/5g/364038/att-and-ibm-co-develop-ai-5g-and-hybrid-cloud-simulation-center",
      "featuredContent": null,
      "highlight": null,
      "heat": 87,
      "tags": null,
      "images": [
        {
          "url": "https://media.itpro.co.uk/image/upload/s--X-WVjvBW--/f_auto,t_content-image-full-desktop@1/v1596721605/itpro/IBM_shutterstock.jpg",
          "width": 1260,
          "height": 710,
          "title": null,
          "attribution": null,
          "isCached": true
        }
      ],
      "content": "\r\n",
      "type": "article",
      "ampWebUrl": null,
      "cdnAmpWebUrl": null,
      "publishedDateTime": "2022-03-01T00:45:00-08:00",
      "updatedDateTime": null,
      "provider": {
        "name": "IT Pro",
        "domain": "itpro.co.uk",
        "images": [
          {
            "url": "https://everyday-cc.github.io/ai/assets/images/organizations/itpro.co.uk-50x50.jpg",
            "width": 50,
            "height": 50,
            "title": null,
            "attribution": null,
            "isCached": false
          }
        ],
        "publishers": null,
        "authors": null
      },
      "locale": "en-us",
      "categories": [
        "news"
      ],
      "topics": [
        "AI"
      ]
    },
    {
      "path": "_news/2022-03-01-starship-technologies-raises-another-42m-to-fuel-the-growth-of-its-fleet-of-self-driving-delivery-robots.md",
      "title": "Starship Technologies raises another $42M to fuel the growth of its fleet of self-driving delivery robots",
      "excerpt": "Starship Technologies, one of the bigger players in the world of autonomous delivery robots — the small, boxy vehicles that self-drive around cities and closed campuses delivering food and other small items — has raised yet another round of funding,",
      "sourceUrl": null,
      "webUrl": "https://techcrunch.com/2022/03/01/starship-technologies-raises-another-42m-to-fuel-the-growth-of-its-fleet-of-self-driving-delivery-robots/",
      "originalUrl": "https://techcrunch.com/2022/03/01/starship-technologies-raises-another-42m-to-fuel-the-growth-of-its-fleet-of-self-driving-delivery-robots/",
      "featuredContent": null,
      "highlight": null,
      "heat": 182,
      "tags": null,
      "images": [
        {
          "url": "https://techcrunch.com/wp-content/uploads/2022/01/Starship-Technologies-2.jpeg?w=840",
          "width": 840,
          "height": 472,
          "title": null,
          "attribution": null,
          "isCached": true
        }
      ],
      "content": "\r\n",
      "type": "article",
      "ampWebUrl": "https://techcrunch.com/2022/03/01/starship-technologies-raises-another-42m-to-fuel-the-growth-of-its-fleet-of-self-driving-delivery-robots/amp/",
      "cdnAmpWebUrl": "https://techcrunch-com.cdn.ampproject.org/c/s/techcrunch.com/2022/03/01/starship-technologies-raises-another-42m-to-fuel-the-growth-of-its-fleet-of-self-driving-delivery-robots/amp/",
      "publishedDateTime": "2022-03-01T00:13:00-08:00",
      "updatedDateTime": null,
      "provider": {
        "name": "TechCrunch",
        "domain": "techcrunch.com",
        "images": [
          {
            "url": "https://everyday-cc.github.io/ai/assets/images/organizations/techcrunch.com-50x50.jpg",
            "width": 50,
            "height": 50,
            "title": null,
            "attribution": null,
            "isCached": false
          }
        ],
        "publishers": null,
        "authors": null
      },
      "locale": "en-us",
      "categories": [
        "news"
      ],
      "topics": [
        "AI in Autos",
        "AI"
      ]
    },
    {
      "path": "_news/2022-03-01-from-artificial-intelligence-to-prison-reform-tuscan-wine-producer-evolving-the-world.md",
      "title": "From Artificial Intelligence To Prison Reform: Tuscan Wine Producer Evolving The World",
      "excerpt": "The Frescobaldi wine family is finding ways to evolve the world around them with using artificial intelligence and advancing prison reform.",
      "sourceUrl": null,
      "webUrl": "https://www.forbes.com/sites/cathrinetodd/2022/02/28/from-artificial-intelligence-to-prison-reform-tuscan-wine-producer-evolving-the-world/",
      "originalUrl": "https://www.forbes.com/sites/cathrinetodd/2022/02/28/from-artificial-intelligence-to-prison-reform-tuscan-wine-producer-evolving-the-world/",
      "featuredContent": null,
      "highlight": null,
      "heat": 89,
      "tags": null,
      "images": [
        {
          "url": "https://imageio.forbes.com/specials-images/imageserve/621d22805039b54e6bdcafc3/0x0.jpg?format=jpg&crop=1756,987,x0,y0,safe&fit=crop",
          "width": 1756,
          "height": 987,
          "title": null,
          "attribution": null,
          "isCached": true
        }
      ],
      "content": "\r\n",
      "type": "article",
      "ampWebUrl": "https://www.forbes.com/sites/cathrinetodd/2022/02/28/from-artificial-intelligence-to-prison-reform-tuscan-wine-producer-evolving-the-world/amp/",
      "cdnAmpWebUrl": "https://www-forbes-com.cdn.ampproject.org/c/s/www.forbes.com/sites/cathrinetodd/2022/02/28/from-artificial-intelligence-to-prison-reform-tuscan-wine-producer-evolving-the-world/amp/",
      "publishedDateTime": "2022-02-28T19:33:00-08:00",
      "updatedDateTime": null,
      "provider": {
        "name": "Forbes",
        "domain": "forbes.com",
        "images": [
          {
            "url": "https://everyday-cc.github.io/ai/assets/images/organizations/forbes.com-50x50.jpg",
            "width": 50,
            "height": 50,
            "title": null,
            "attribution": null,
            "isCached": false
          }
        ],
        "publishers": null,
        "authors": null
      },
      "locale": "en-us",
      "categories": [
        "news"
      ],
      "topics": [
        "AI"
      ]
    },
    {
      "path": "_news/2022-03-01-energy-efficient-ai-semiconductor-company-edgecortix-closes-series-a-funding.md",
      "title": "Energy-efficient AI Semiconductor Company EdgeCortix Closes Series A Funding",
      "excerpt": "EdgeCortix® the AI-focused fabless semiconductor company today announced that it has closed over $8 Million USD in series A",
      "sourceUrl": null,
      "webUrl": "https://www.asiaone.com/business/energy-efficient-ai-semiconductor-company-edgecortix-closes-series-funding",
      "originalUrl": "https://www.asiaone.com/business/energy-efficient-ai-semiconductor-company-edgecortix-closes-series-funding",
      "featuredContent": null,
      "highlight": null,
      "heat": 76,
      "tags": null,
      "images": [
        {
          "url": "https://www.asiaone.com/sites/default/files/styles/a1_og_image/public/original_images/Mar2022/pr-newswire_500_4_37.jpg?itok=bxgOz32L",
          "width": 763,
          "height": 509,
          "title": null,
          "attribution": null,
          "isCached": true
        }
      ],
      "content": "\r\n",
      "type": "article",
      "ampWebUrl": "https://www.asiaone.com/business/energy-efficient-ai-semiconductor-company-edgecortix-closes-series-funding?amp",
      "cdnAmpWebUrl": "https://www-asiaone-com.cdn.ampproject.org/c/s/www.asiaone.com/business/energy-efficient-ai-semiconductor-company-edgecortix-closes-series-funding?amp",
      "publishedDateTime": "2022-02-28T17:00:00-08:00",
      "updatedDateTime": null,
      "provider": {
        "name": "Asia One",
        "domain": "asiaone.com",
        "images": null,
        "publishers": null,
        "authors": null
      },
      "locale": "en-us",
      "categories": [
        "news"
      ],
      "topics": [
        "AI Hardware",
        "AI"
      ]
    },
    {
      "path": "_news/2022-03-01-chinese-self-driving-truck-startup-secures-188-million-in-funding-from-sequoia-china-and-legend-capital.md",
      "title": "Chinese Self-Driving Truck Startup Secures $188 Million In Funding From Sequoia China And Legend Capital",
      "excerpt": "China’s Ministry of Industry and Information Technology rolled out guidelines for autonomous vehicles last April, encouraging local governments to open highways and roads for testing self-driving cars.",
      "sourceUrl": null,
      "webUrl": "https://www.forbes.com/sites/catherinewang/2022/03/01/chinese-self-driving-truck-startup-secures-188-million-in-funding-from-sequoia-china-and-legend-capital/",
      "originalUrl": "https://www.forbes.com/sites/catherinewang/2022/03/01/chinese-self-driving-truck-startup-secures-188-million-in-funding-from-sequoia-china-and-legend-capital/",
      "featuredContent": null,
      "highlight": null,
      "heat": 87,
      "tags": null,
      "images": [
        {
          "url": "https://imageio.forbes.com/specials-images/imageserve/621dd187b8e605f51c6f0b4d/0x0.jpg?format=jpg&crop=2461,1641,x0,y174,safe&fit=crop",
          "width": 2461,
          "height": 1641,
          "title": null,
          "attribution": null,
          "isCached": true
        }
      ],
      "content": "\r\n",
      "type": "article",
      "ampWebUrl": "https://www.forbes.com/sites/catherinewang/2022/03/01/chinese-self-driving-truck-startup-secures-188-million-in-funding-from-sequoia-china-and-legend-capital/amp/",
      "cdnAmpWebUrl": "https://www-forbes-com.cdn.ampproject.org/c/s/www.forbes.com/sites/catherinewang/2022/03/01/chinese-self-driving-truck-startup-secures-188-million-in-funding-from-sequoia-china-and-legend-capital/amp/",
      "publishedDateTime": "2022-02-28T16:00:00-08:00",
      "updatedDateTime": null,
      "provider": {
        "name": "Forbes",
        "domain": "forbes.com",
        "images": [
          {
            "url": "https://everyday-cc.github.io/ai/assets/images/organizations/forbes.com-50x50.jpg",
            "width": 50,
            "height": 50,
            "title": null,
            "attribution": null,
            "isCached": false
          }
        ],
        "publishers": null,
        "authors": null
      },
      "locale": "en-us",
      "categories": [
        "news"
      ],
      "topics": [
        "AI in Autos",
        "AI"
      ]
    },
    {
      "path": "_news/2022-03-01-here-comes-the-full-amazonification-of-whole-foods.md",
      "title": "Here Comes the Full Amazonification of Whole Foods",
      "excerpt": "A newly revamped store in Washington shows how thoroughly Amazon has woven itself into the grocery shopping experience.",
      "sourceUrl": null,
      "webUrl": "https://www.nytimes.com/2022/02/28/technology/whole-foods-amazon-automation.html",
      "originalUrl": "https://www.nytimes.com/2022/02/28/technology/whole-foods-amazon-automation.html",
      "featuredContent": null,
      "highlight": null,
      "heat": 172,
      "tags": null,
      "images": [
        {
          "url": "https://static01.nyt.com/images/2022/02/24/business/00wholefoods2/00wholefoods2-facebookJumbo.jpg",
          "width": 1050,
          "height": 550,
          "title": null,
          "attribution": null,
          "isCached": true
        }
      ],
      "content": "\r\n",
      "type": "article",
      "ampWebUrl": "https://www.nytimes.com/2022/02/28/technology/whole-foods-amazon-automation.amp.html",
      "cdnAmpWebUrl": "https://www-nytimes-com.cdn.ampproject.org/c/s/www.nytimes.com/2022/02/28/technology/whole-foods-amazon-automation.amp.html",
      "publishedDateTime": "2022-02-28T13:25:00-08:00",
      "updatedDateTime": null,
      "provider": {
        "name": "New York Times",
        "domain": "nytimes.com",
        "images": [
          {
            "url": "/assets/images/organizations/nytimes.com-50x50.jpg",
            "width": 50,
            "height": 50,
            "title": null,
            "attribution": null,
            "isCached": false
          }
        ],
        "publishers": null,
        "authors": null
      },
      "locale": "en-us",
      "categories": [
        "news"
      ],
      "topics": [
        "AI"
      ]
    },
    {
      "path": "_news/2022-03-01-corticalio-adds-contract-intelligence-to-document-processing.md",
      "title": "Cortical.io adds contract intelligence to document processing",
      "excerpt": "This technology leverages such tools as computer vision, machine learning, natural language processing, and optical character recognition. But when it comes to delving deeper into more complex ...",
      "sourceUrl": null,
      "webUrl": "https://venturebeat.com/2022/02/28/cortical-io-adds-contract-intelligence-to-document-processing/",
      "originalUrl": "https://venturebeat.com/2022/02/28/cortical-io-adds-contract-intelligence-to-document-processing/",
      "featuredContent": null,
      "highlight": null,
      "heat": 84,
      "tags": null,
      "images": [
        {
          "url": "https://venturebeat.com/wp-content/uploads/2022/02/GettyImages-1354189829-1-e1646064906433.jpg?fit=800%2C533&strip=all",
          "width": 800,
          "height": 450,
          "title": null,
          "attribution": null,
          "isCached": true
        }
      ],
      "content": "\r\n",
      "type": "article",
      "ampWebUrl": "https://venturebeat.com/2022/02/28/cortical-io-adds-contract-intelligence-to-document-processing/amp/",
      "cdnAmpWebUrl": "https://venturebeat-com.cdn.ampproject.org/c/s/venturebeat.com/2022/02/28/cortical-io-adds-contract-intelligence-to-document-processing/amp/",
      "publishedDateTime": "2022-02-28T13:20:00-08:00",
      "updatedDateTime": null,
      "provider": {
        "name": "VentureBeat",
        "domain": "venturebeat.com",
        "images": [
          {
            "url": "https://everyday-cc.github.io/ai/assets/images/organizations/venturebeat.com-50x50.jpg",
            "width": 50,
            "height": 50,
            "title": null,
            "attribution": null,
            "isCached": false
          }
        ],
        "publishers": null,
        "authors": null
      },
      "locale": "en-us",
      "categories": [
        "news"
      ],
      "topics": [
        "Natural Language Processing",
        "AI"
      ]
    },
    {
      "path": "_news/2022-03-01-tesla-begins-rolling-out-full-self-driving-fsd-beta-in-canada.md",
      "title": "Tesla begins rolling out Full Self-Driving FSD Beta in Canada",
      "excerpt": "Tesla begins rolling out Full Self-Driving FSD Beta in Canada. Only users who actively apply and pass their \"Security Test Score\" can try it",
      "sourceUrl": null,
      "webUrl": "https://www.gizchina.com/2022/02/28/tesla-begins-rolling-out-full-self-driving-fsd-beta-in-canada/",
      "originalUrl": "https://www.gizchina.com/2022/02/28/tesla-begins-rolling-out-full-self-driving-fsd-beta-in-canada/",
      "featuredContent": null,
      "highlight": null,
      "heat": 89,
      "tags": null,
      "images": [
        {
          "url": "https://www.gizchina.com/wp-content/uploads/images/2022/02/Tesla-Autopilot-a-1024x576.jpg",
          "width": 1024,
          "height": 576,
          "title": null,
          "attribution": null,
          "isCached": true
        }
      ],
      "content": "\r\n",
      "type": "article",
      "ampWebUrl": "https://www.gizchina.com/2022/02/28/tesla-begins-rolling-out-full-self-driving-fsd-beta-in-canada/amp/",
      "cdnAmpWebUrl": "https://www-gizchina-com.cdn.ampproject.org/c/s/www.gizchina.com/2022/02/28/tesla-begins-rolling-out-full-self-driving-fsd-beta-in-canada/amp/",
      "publishedDateTime": "2022-02-28T11:52:00-08:00",
      "updatedDateTime": null,
      "provider": {
        "name": "GizChina",
        "domain": "gizchina.com",
        "images": null,
        "publishers": null,
        "authors": null
      },
      "locale": "en-us",
      "categories": [
        "news"
      ],
      "topics": [
        "AI in Autos",
        "AI"
      ]
    },
    {
      "path": "_news/2022-03-01-speech-recognition-market-growth-rate-top-players-analysis-statistics-revenue-and-forecast-till-2028.md",
      "title": "Speech Recognition Market Growth Rate, Top Players Analysis, Statistics, Revenue and Forecast till 2028",
      "excerpt": "Market Study Report Adds New Research On Speech Recognition Market, Which Is A Detailed Analysis Of This Business Space Inclusive Of The Trends, Competitive Landscape, And The Market Size. Encompassing One Or More Parameters Among Product Analysis,",
      "sourceUrl": null,
      "webUrl": "https://www.marketwatch.com/press-release/speech-recognition-market-growth-rate-top-players-analysis-statistics-revenue-and-forecast-till-2028-2022-02-28",
      "originalUrl": "https://www.marketwatch.com/press-release/speech-recognition-market-growth-rate-top-players-analysis-statistics-revenue-and-forecast-till-2028-2022-02-28",
      "featuredContent": null,
      "highlight": null,
      "heat": 173,
      "tags": null,
      "images": [
        {
          "url": "https://mw3.wsj.net/mw5/content/logos/mw_logo_social.png",
          "width": 1200,
          "height": 630,
          "title": null,
          "attribution": null,
          "isCached": true
        }
      ],
      "content": "\r\n",
      "type": "article",
      "ampWebUrl": null,
      "cdnAmpWebUrl": null,
      "publishedDateTime": "2022-02-28T11:11:00-08:00",
      "updatedDateTime": null,
      "provider": {
        "name": "MarketWatch",
        "domain": "marketwatch.com",
        "images": [
          {
            "url": "https://everyday-cc.github.io/ai/assets/images/organizations/marketwatch.com-50x50.jpg",
            "width": 50,
            "height": 50,
            "title": null,
            "attribution": null,
            "isCached": false
          }
        ],
        "publishers": null,
        "authors": null
      },
      "locale": "en-us",
      "categories": [
        "news"
      ],
      "topics": [
        "Natural Language Processing",
        "AI"
      ]
    }
  ],
  "nextPage": 5
}