{
  "page": 26,
  "value": [
    {
      "path": "_news/2021-12-22-ethics-at-the-heart-of-emerging-ai-strategies.md",
      "title": "Ethics at the heart of emerging AI strategies",
      "excerpt": "But there remain concerns around the rapid spread of AI, and there is an increasing focus on the ethics surrounding the technology.  While AI is forecast to deliver as much as a 10% boost to the UK economy over the next decade,",
      "sourceUrl": null,
      "webUrl": "https://www.computerweekly.com/ehandbook/Ethics-at-the-heart-of-emerging-AI-strategies",
      "originalUrl": "https://www.computerweekly.com/ehandbook/Ethics-at-the-heart-of-emerging-AI-strategies",
      "featuredContent": null,
      "highlight": null,
      "heat": null,
      "tags": null,
      "images": [
        {
          "url": "https://cdn.ttgtmedia.com/rms/computerweekly/Cover_Ethic_at_the_heart_of_emerging_AI_strategies.png",
          "width": 883,
          "height": 590,
          "title": null,
          "attribution": null,
          "isCached": true
        }
      ],
      "content": "\r\n",
      "type": "article",
      "ampWebUrl": null,
      "cdnAmpWebUrl": null,
      "publishedDateTime": "2021-12-22T03:59:00-08:00",
      "updatedDateTime": null,
      "provider": {
        "name": "Computer Weekly",
        "domain": "computerweekly.com",
        "images": null,
        "publishers": null,
        "authors": null
      },
      "locale": "en-us",
      "categories": [
        "news"
      ],
      "topics": [
        "AI Ethics",
        "AI"
      ]
    },
    {
      "path": "_news/2021-12-22-can-ai-actually-understand-what-we-are-saying-scientists-are-divided.md",
      "title": "Can AI actually understand what we are saying? Scientists are divided",
      "excerpt": "Scientists argue that large language models can teach us about “the nature of language, understanding, intelligence, sociality, and personhood\"",
      "sourceUrl": null,
      "webUrl": "https://thenextweb.com/news/ai-understand-what-we-are-saying-scientists-divided-syndication",
      "originalUrl": "https://thenextweb.com/news/ai-understand-what-we-are-saying-scientists-divided-syndication",
      "featuredContent": null,
      "highlight": null,
      "heat": 81,
      "tags": null,
      "images": [
        {
          "url": "https://img-cdn.tnwcdn.com/image/neural?filter_last=1&fit=1280%2C640&url=https%3A%2F%2Fcdn0.tnwcdn.com%2Fwp-content%2Fblogs.dir%2F1%2Ffiles%2F2021%2F12%2FBDHedjpg.jpg&signature=a835e3cfd92b6b341294a40ee9c66e9b",
          "width": 1280,
          "height": 640,
          "title": null,
          "attribution": null,
          "isCached": true
        }
      ],
      "content": "\r\n",
      "type": "article",
      "ampWebUrl": null,
      "cdnAmpWebUrl": null,
      "publishedDateTime": "2021-12-22T03:55:00-08:00",
      "updatedDateTime": null,
      "provider": {
        "name": "The Next Web",
        "domain": "thenextweb.com",
        "images": [
          {
            "url": "https://everyday-cc.github.io/ai/assets/images/organizations/thenextweb.com-50x50.jpg",
            "width": 50,
            "height": 50,
            "title": null,
            "attribution": null,
            "isCached": false
          }
        ],
        "publishers": null,
        "authors": null
      },
      "locale": "en-us",
      "categories": [
        "news"
      ],
      "topics": [
        "Natural Language Processing",
        "AI",
        "Machine Learning"
      ]
    },
    {
      "path": "_news/2021-12-22-how-to-use-the-power-of-ai-for-marketing-success.md",
      "title": "How To Use The Power Of AI For Marketing Success",
      "excerpt": "Marketing has evolved over the past decades, and we’re now in an era of digital revolution where marketing is completely dependent on consumers who dictate what content they want to receive.",
      "sourceUrl": null,
      "webUrl": "https://www.forbes.com/sites/forbestechcouncil/2021/12/22/how-to-use-the-power-of-ai-for-marketing-success/",
      "originalUrl": "https://www.forbes.com/sites/forbestechcouncil/2021/12/22/how-to-use-the-power-of-ai-for-marketing-success/",
      "featuredContent": null,
      "highlight": null,
      "heat": 154,
      "tags": null,
      "images": [
        {
          "url": "https://thumbor.forbes.com/thumbor/fit-in/1200x0/filters%3Aformat%28jpg%29/https%3A%2F%2Fspecials-images.forbesimg.com%2Fimageserve%2F61c1d51a170ebe018990edc6%2F0x0.jpg",
          "width": 1161,
          "height": 774,
          "title": null,
          "attribution": null,
          "isCached": true
        }
      ],
      "content": "\r\n",
      "type": "article",
      "ampWebUrl": "https://www.forbes.com/sites/forbestechcouncil/2021/12/22/how-to-use-the-power-of-ai-for-marketing-success/amp/",
      "cdnAmpWebUrl": "https://www-forbes-com.cdn.ampproject.org/c/s/www.forbes.com/sites/forbestechcouncil/2021/12/22/how-to-use-the-power-of-ai-for-marketing-success/amp/",
      "publishedDateTime": "2021-12-22T03:15:00-08:00",
      "updatedDateTime": null,
      "provider": {
        "name": "Forbes",
        "domain": "forbes.com",
        "images": [
          {
            "url": "https://everyday-cc.github.io/ai/assets/images/organizations/forbes.com-50x50.jpg",
            "width": 50,
            "height": 50,
            "title": null,
            "attribution": null,
            "isCached": false
          }
        ],
        "publishers": null,
        "authors": null
      },
      "locale": "en-us",
      "categories": [
        "news"
      ],
      "topics": [
        "AI",
        "AI in Marketing"
      ]
    },
    {
      "path": "_news/2021-12-22-campuses-law-enforcement-reckon-with-facial-recognition-bans.md",
      "title": "Campuses, Law Enforcement Reckon with Facial Recognition Bans",
      "excerpt": "Implementing facial recognition is becoming more cumbersome as an increasing number of cities and states restrict the use of this technology.",
      "sourceUrl": null,
      "webUrl": "https://www.campussafetymagazine.com/news/campuses-law-enforcement-reckon-with-facial-recognition-bans/",
      "originalUrl": "https://www.campussafetymagazine.com/news/campuses-law-enforcement-reckon-with-facial-recognition-bans/",
      "featuredContent": null,
      "highlight": null,
      "heat": 189,
      "tags": null,
      "images": [
        {
          "url": "https://www.campussafetymagazine.com/wp-content/uploads/2021/12/Facial-recogntion-Adobe-by-Fractal-Pictures-scaled.jpeg",
          "width": 2560,
          "height": 1440,
          "title": null,
          "attribution": null,
          "isCached": true
        }
      ],
      "content": "\r\n",
      "type": "article",
      "ampWebUrl": null,
      "cdnAmpWebUrl": null,
      "publishedDateTime": "2021-12-22T02:40:00-08:00",
      "updatedDateTime": null,
      "provider": {
        "name": "Campus Safety Magazine",
        "domain": "campussafetymagazine.com",
        "images": null,
        "publishers": null,
        "authors": null
      },
      "locale": "en-us",
      "categories": [
        "news"
      ],
      "topics": [
        "Computer Vision",
        "AI"
      ]
    },
    {
      "path": "_news/2021-12-22-the-global-image-recognition-market-stood-at-usd27764-billion-in-2020-and-is-growing-with-a-cagr-of-1759-to-reach-usd73344-billion-by-2026.md",
      "title": "The global image recognition market stood at USD27.764 billion in 2020 and is growing with a CAGR of 17.59% to reach USD73.344 billion by 2026",
      "excerpt": "Reportlinker.com announces the release of the report \"Global Image Recognition Market, By Component, By Technology,",
      "sourceUrl": null,
      "webUrl": "https://www.benzinga.com/pressreleases/21/12/g24734672/the-global-image-recognition-market-stood-at-usd27-764-billion-in-2020-and-is-growing-with-a-cagr-",
      "originalUrl": "https://www.benzinga.com/pressreleases/21/12/g24734672/the-global-image-recognition-market-stood-at-usd27-764-billion-in-2020-and-is-growing-with-a-cagr-",
      "featuredContent": null,
      "highlight": null,
      "heat": null,
      "tags": null,
      "images": null,
      "content": "\r\n",
      "type": "article",
      "ampWebUrl": "https://www.benzinga.com/amp/content/24734672",
      "cdnAmpWebUrl": "https://www-benzinga-com.cdn.ampproject.org/c/s/www.benzinga.com/amp/content/24734672",
      "publishedDateTime": "2021-12-22T02:11:00-08:00",
      "updatedDateTime": null,
      "provider": {
        "name": "Benzinga.com",
        "domain": "benzinga.com",
        "images": null,
        "publishers": null,
        "authors": null
      },
      "locale": "en-us",
      "categories": [
        "news"
      ],
      "topics": [
        "Computer Vision",
        "AI"
      ]
    },
    {
      "path": "_news/2021-12-22-cars-are-getting-better-at-driving-themselves-but-you-still-cant-sit-back-and-nap.md",
      "title": "Cars are getting better at driving themselves, but you still can't sit back and nap",
      "excerpt": "\"There are exactly zero self-driving cars available for purchase ... they can have clear safety benefits. Baidu Apollo Robotaxis move on a street in Beijing on May 2. Chinese tech giant Baidu ...",
      "sourceUrl": null,
      "webUrl": "https://www.wshu.org/npr-news/2021-12-22/cars-are-getting-better-at-driving-themselves-but-you-still-cant-sit-back-and-nap",
      "originalUrl": "https://www.wshu.org/npr-news/2021-12-22/cars-are-getting-better-at-driving-themselves-but-you-still-cant-sit-back-and-nap",
      "featuredContent": null,
      "highlight": null,
      "heat": null,
      "tags": null,
      "images": [
        {
          "url": "https://npr.brightspotcdn.com/dims4/default/6b99e63/2147483647/strip/true/crop/3205x1974+0+213/resize/880x542!/quality/90/?url=https%3A%2F%2Fmedia.npr.org%2Fassets%2Fimg%2F2021%2F12%2F20%2Fap_21140129870069-852dfa883cd757930c04f9432840a9c0f8044504.jpg",
          "width": 880,
          "height": 542,
          "title": null,
          "attribution": null,
          "isCached": true
        }
      ],
      "content": "\r\n",
      "type": "article",
      "ampWebUrl": "https://www.wshu.org/npr-news/2021-12-22/cars-are-getting-better-at-driving-themselves-but-you-still-cant-sit-back-and-nap?_amp=true",
      "cdnAmpWebUrl": "https://www-wshu-org.cdn.ampproject.org/c/s/www.wshu.org/npr-news/2021-12-22/cars-are-getting-better-at-driving-themselves-but-you-still-cant-sit-back-and-nap?_amp=true",
      "publishedDateTime": "2021-12-22T02:07:00-08:00",
      "updatedDateTime": null,
      "provider": {
        "name": "WSHU news",
        "domain": "wshu.org",
        "images": null,
        "publishers": null,
        "authors": null
      },
      "locale": "en-us",
      "categories": [
        "news"
      ],
      "topics": [
        "AI in Autos",
        "AI"
      ]
    },
    {
      "path": "_news/2021-12-22-tesla-stock-recent-self-driving-success-promises-a-smooth-road-ahead.md",
      "title": "Tesla Stock: Recent Self-Driving Success Promises a Smooth Road Ahead",
      "excerpt": "Source: Hadrian / Shutterstock.com While a future with ubiquitous self-driving vehicles is likely years away, companies are working hard to be first in line. And Tesla is certainly among them. As the leader of the EV race,",
      "sourceUrl": null,
      "webUrl": "https://www.nasdaq.com/articles/tesla-stock%3A-recent-self-driving-success-promises-a-smooth-road-ahead",
      "originalUrl": "https://www.nasdaq.com/articles/tesla-stock%3A-recent-self-driving-success-promises-a-smooth-road-ahead",
      "featuredContent": null,
      "highlight": null,
      "heat": null,
      "tags": null,
      "images": null,
      "content": "\r\n",
      "type": "article",
      "ampWebUrl": "https://www.nasdaq.com/articles/tesla-stock%3A-recent-self-driving-success-promises-a-smooth-road-ahead?amp",
      "cdnAmpWebUrl": "https://www-nasdaq-com.cdn.ampproject.org/c/s/www.nasdaq.com/articles/tesla-stock%3A-recent-self-driving-success-promises-a-smooth-road-ahead?amp",
      "publishedDateTime": "2021-12-22T00:47:00-08:00",
      "updatedDateTime": null,
      "provider": {
        "name": "Nasdaq",
        "domain": "nasdaq.com",
        "images": null,
        "publishers": null,
        "authors": null
      },
      "locale": "en-us",
      "categories": [
        "news"
      ],
      "topics": [
        "AI in Autos",
        "AI"
      ]
    },
    {
      "path": "_news/2021-12-22-santas-christmas-secret-maybe-its-artificial-intelligence.md",
      "title": "Santa’s Christmas secret? Maybe it’s artificial intelligence",
      "excerpt": "AI’s ability to collect and analyze massive amounts of data has plenty of applications – including sorting millions of children as either naughty or nice",
      "sourceUrl": null,
      "webUrl": "https://www.theglobeandmail.com/opinion/article-santas-christmas-secret-maybe-its-artificial-intelligence/",
      "originalUrl": "https://www.theglobeandmail.com/opinion/article-santas-christmas-secret-maybe-its-artificial-intelligence/",
      "featuredContent": null,
      "highlight": null,
      "heat": 119,
      "tags": null,
      "images": [
        {
          "url": "https://www.theglobeandmail.com/resizer/AOKpBVKlFz80JsC4iDqS036mcBo=/1200x863/filters:quality(80)/cloudfront-us-east-1.images.arcpublishing.com/tgam/HASE5WN2KNFEXJ76HO6LG6GTCM",
          "width": 1200,
          "height": 863,
          "title": null,
          "attribution": null,
          "isCached": true
        }
      ],
      "content": "\r\n",
      "type": "article",
      "ampWebUrl": "https://www.theglobeandmail.com/amp/opinion/article-santas-christmas-secret-maybe-its-artificial-intelligence/",
      "cdnAmpWebUrl": "https://www-theglobeandmail-com.cdn.ampproject.org/c/s/www.theglobeandmail.com/amp/opinion/article-santas-christmas-secret-maybe-its-artificial-intelligence/",
      "publishedDateTime": "2021-12-22T00:00:00-08:00",
      "updatedDateTime": null,
      "provider": {
        "name": "The Globe and Mail",
        "domain": "theglobeandmail.com",
        "images": null,
        "publishers": null,
        "authors": null
      },
      "locale": "en-us",
      "categories": [
        "news"
      ],
      "topics": [
        "AI in Robotics",
        "AI"
      ]
    },
    {
      "path": "_news/2021-12-22-uae-self-driving-taxis-txai-to-transport-passengers-on-abu-dhabis-yas-island.md",
      "title": "UAE: Self-driving taxis ‘TXAI’ to transport passengers on Abu Dhabi’s Yas Island",
      "excerpt": "Commuters in Abu Dhabi can now travel on driverless taxis round the clock through the ‘TXAI’ app, available on Google Play and IOS App Store. Hassan Al Hosani, CEO of Bayanat for Mapping and Surveying Services,",
      "sourceUrl": null,
      "webUrl": "https://gulfnews.com/uae/transport/uae-self-driving-taxis-txai-to-transport-passengers-on-abu-dhabis-yas-island-1.84553816",
      "originalUrl": "https://gulfnews.com/uae/transport/uae-self-driving-taxis-txai-to-transport-passengers-on-abu-dhabis-yas-island-1.84553816",
      "featuredContent": null,
      "highlight": null,
      "heat": 94,
      "tags": null,
      "images": [
        {
          "url": "https://imagevars.gulfnews.com/2021/12/22/Txai-1_17de0e47d18_medium.jpg",
          "width": 540,
          "height": 405,
          "title": null,
          "attribution": null,
          "isCached": true
        }
      ],
      "content": "\r\n",
      "type": "article",
      "ampWebUrl": "https://gulfnews.com/amp/uae/transport/uae-self-driving-taxis-txai-to-transport-passengers-on-abu-dhabis-yas-island-1.84553816",
      "cdnAmpWebUrl": "https://gulfnews-com.cdn.ampproject.org/c/s/gulfnews.com/amp/uae/transport/uae-self-driving-taxis-txai-to-transport-passengers-on-abu-dhabis-yas-island-1.84553816",
      "publishedDateTime": "2021-12-21T22:25:00-08:00",
      "updatedDateTime": null,
      "provider": {
        "name": "Gulf News",
        "domain": "gulfnews.com",
        "images": null,
        "publishers": null,
        "authors": null
      },
      "locale": "en-us",
      "categories": [
        "news"
      ],
      "topics": [
        "AI in Autos",
        "AI"
      ]
    },
    {
      "path": "_news/2021-12-22-self-driving-startup-haomo-raises-rmb-1-billion-reaches-unicorn-status.md",
      "title": "Self-driving startup Haomo raises RMB 1 billion, reaches unicorn status",
      "excerpt": "Chinese self-driving startup Haomo announced Tuesday it has secured a RMB 1 billion (around $157 million) Series A from investors including GL Ventures, the early-stage investment arm of private equity firm Hillhouse Capital,",
      "sourceUrl": null,
      "webUrl": "https://technode.com/2021/12/22/self-driving-startup-haomo-raises-rmb-1-billion-reaches-unicorn-status/",
      "originalUrl": "https://technode.com/2021/12/22/self-driving-startup-haomo-raises-rmb-1-billion-reaches-unicorn-status/",
      "featuredContent": null,
      "highlight": null,
      "heat": 179,
      "tags": null,
      "images": [
        {
          "url": "https://i0.wp.com/technode.com/wp-content/uploads/2021/08/technode-news-feed-1-1.png?fit=540%2C540&ssl=1",
          "width": 540,
          "height": 540,
          "title": null,
          "attribution": null,
          "isCached": true
        }
      ],
      "content": "\r\n",
      "type": "article",
      "ampWebUrl": "https://technode.com/2021/12/22/self-driving-startup-haomo-raises-rmb-1-billion-reaches-unicorn-status/",
      "cdnAmpWebUrl": "https://technode-com.cdn.ampproject.org/c/s/technode.com/2021/12/22/self-driving-startup-haomo-raises-rmb-1-billion-reaches-unicorn-status/",
      "publishedDateTime": "2021-12-21T22:01:00-08:00",
      "updatedDateTime": null,
      "provider": {
        "name": "TechNode",
        "domain": "technode.com",
        "images": null,
        "publishers": null,
        "authors": null
      },
      "locale": "en-us",
      "categories": [
        "news"
      ],
      "topics": [
        "AI in Autos",
        "AI"
      ]
    },
    {
      "path": "_news/2021-12-22-supply-chain-startup-unbox-bags-7-mn-infusion-to-build-compact-ecommerce-robotics-solutions.md",
      "title": "Supply Chain Startup Unbox Bags $7 Mn Infusion To Build Compact Ecommerce Robotics Solutions",
      "excerpt": "Supply-chain robotics startup Unbox Robotics has raised $7 Mn in a Series A funding round led by 3one4 Capital.",
      "sourceUrl": null,
      "webUrl": "https://inc42.com/buzz/unbox-bags-7-mn-to-build-compact-ecommerce-robotics-solutions/",
      "originalUrl": "https://inc42.com/buzz/unbox-bags-7-mn-to-build-compact-ecommerce-robotics-solutions/",
      "featuredContent": null,
      "highlight": null,
      "heat": 78,
      "tags": null,
      "images": [
        {
          "url": "https://inc42.com/wp-content/uploads/2021/12/unbox-social.jpg",
          "width": 1200,
          "height": 628,
          "title": null,
          "attribution": null,
          "isCached": true
        }
      ],
      "content": "\r\n",
      "type": "article",
      "ampWebUrl": "https://inc42.com/buzz/unbox-bags-7-mn-to-build-compact-ecommerce-robotics-solutions/amp/",
      "cdnAmpWebUrl": "https://inc42-com.cdn.ampproject.org/c/s/inc42.com/buzz/unbox-bags-7-mn-to-build-compact-ecommerce-robotics-solutions/amp/",
      "publishedDateTime": "2021-12-21T21:59:00-08:00",
      "updatedDateTime": null,
      "provider": {
        "name": "inc42.com",
        "domain": "inc42.com",
        "images": null,
        "publishers": null,
        "authors": null
      },
      "locale": "en-us",
      "categories": [
        "news"
      ],
      "topics": [
        "AI in Robotics",
        "AI"
      ]
    },
    {
      "path": "_news/2021-12-22-can-ai-tell-a-good-story.md",
      "title": "Can AI tell a good story?",
      "excerpt": "Deep-Story: Artificial Intelligence and Next Generation Storytelling I am an author and screenwriter and love the creative process – from the first inspiration to the finished book and film. Currently the mystical dance with the muse can take years and includes many highs and even more lows which test the perseverance of the writer.",
      "sourceUrl": null,
      "webUrl": "https://www.innovatorsmag.com/can-ai-tell-a-good-story/",
      "originalUrl": "https://www.innovatorsmag.com/can-ai-tell-a-good-story/",
      "featuredContent": null,
      "highlight": null,
      "heat": null,
      "tags": null,
      "images": [
        {
          "url": "https://www.innovatorsmag.com/wp-content/uploads/2021/12/etienne-girardet-EP6_VZhzXM8-unsplash-scaled.jpg",
          "width": 2560,
          "height": 1920,
          "title": null,
          "attribution": null,
          "isCached": true
        }
      ],
      "content": "\r\n",
      "type": "article",
      "ampWebUrl": "https://www.innovatorsmag.com/can-ai-tell-a-good-story/amp/",
      "cdnAmpWebUrl": "https://www-innovatorsmag-com.cdn.ampproject.org/c/s/www.innovatorsmag.com/can-ai-tell-a-good-story/amp/",
      "publishedDateTime": "2021-12-21T20:22:00-08:00",
      "updatedDateTime": null,
      "provider": {
        "name": "innovatorsmag.com",
        "domain": "innovatorsmag.com",
        "images": null,
        "publishers": null,
        "authors": null
      },
      "locale": "en-us",
      "categories": [
        "news"
      ],
      "topics": [
        "AI Ethics",
        "AI"
      ]
    },
    {
      "path": "_news/2021-12-22-explore-amazon-sagemaker-serverless-inference-for-deploying-ml-models.md",
      "title": "Explore Amazon SageMaker Serverless Inference for Deploying ML Models",
      "excerpt": "Invent 2021 user conference earlier this month, Amazon Web Services‘ Amazon SageMaker Serverless Inference is a new inference option to deploy machine learning models without configuring and managing the compute infrastructure.",
      "sourceUrl": null,
      "webUrl": "https://www.linkedin.com/pulse/explore-amazon-sagemaker-serverless-inference-deploying-janakiram-msv",
      "originalUrl": "https://www.linkedin.com/pulse/explore-amazon-sagemaker-serverless-inference-deploying-janakiram-msv",
      "featuredContent": null,
      "highlight": null,
      "heat": null,
      "tags": null,
      "images": [
        {
          "url": "https://media-exp1.licdn.com/dms/image/C4D12AQF_v9S4FOAWYQ/article-cover_image-shrink_600_2000/0/1640146369662?e=1646870400&v=beta&t=7XPeAvELZF1fxTTBuiJ3JdPVUs4qxJgnjMSIh3-SWd4",
          "width": 640,
          "height": 439,
          "title": null,
          "attribution": null,
          "isCached": true
        }
      ],
      "content": "\r\n",
      "type": "article",
      "ampWebUrl": null,
      "cdnAmpWebUrl": null,
      "publishedDateTime": "2021-12-21T20:16:00-08:00",
      "updatedDateTime": null,
      "provider": {
        "name": "LinkedIn",
        "domain": "linkedin.com",
        "images": [
          {
            "url": "https://everyday-cc.github.io/ai/assets/images/organizations/linkedin.com-50x50.jpg",
            "width": 50,
            "height": 50,
            "title": null,
            "attribution": null,
            "isCached": false
          }
        ],
        "publishers": null,
        "authors": null
      },
      "locale": "en-us",
      "categories": [
        "news"
      ],
      "topics": [
        "AWS AI",
        "AI",
        "Machine Learning"
      ]
    },
    {
      "path": "_news/2021-12-22-advent-international-acquires-majority-stake-in-encora-a-leading-provider-of-digital-engineering-services.md",
      "title": "Advent International Acquires Majority Stake in Encora, a Leading Provider of Digital Engineering Services",
      "excerpt": "Encora, a global digital engineering services company specializing in software product development services for fast-growing enterprises and digitally-native companies and Advent International (\"Advent\"),",
      "sourceUrl": null,
      "webUrl": "https://www.newswit.com/en/LRbT",
      "originalUrl": "https://www.newswit.com/en/LRbT",
      "featuredContent": null,
      "highlight": null,
      "heat": null,
      "tags": null,
      "images": null,
      "content": "\r\n",
      "type": "article",
      "ampWebUrl": null,
      "cdnAmpWebUrl": null,
      "publishedDateTime": "2021-12-21T17:00:00-08:00",
      "updatedDateTime": null,
      "provider": {
        "name": "academy",
        "domain": "newswit.com",
        "images": null,
        "publishers": null,
        "authors": null
      },
      "locale": "en-us",
      "categories": [
        "news"
      ],
      "topics": [
        "AI in Finance",
        "AI"
      ]
    },
    {
      "path": "_news/2021-12-22-waymo-adds-750-million-to-war-chest-as-driverless-cars-prove-tough-to-deploy.md",
      "title": "Waymo Adds $750 Million to War Chest as Driverless Cars Prove Tough to Deploy",
      "excerpt": "In the world of driverless cars, the big keep getting ... are going to big companies rather than unproven startups as the artificial intelligence technology has proven harder to deploy than ...",
      "sourceUrl": null,
      "webUrl": "https://br.advfn.com/noticias/DJN/2020/artigo/82437841",
      "originalUrl": "https://br.advfn.com/noticias/DJN/2020/artigo/82437841",
      "featuredContent": null,
      "highlight": null,
      "heat": null,
      "tags": null,
      "images": [
        {
          "url": "https://br.advfn.com/p.php?pid=staticchart&s=NASDAQ:GOOG&p=5&t=52",
          "width": 1200,
          "height": 630,
          "title": null,
          "attribution": null,
          "isCached": true
        }
      ],
      "content": "\r\n",
      "type": "article",
      "ampWebUrl": null,
      "cdnAmpWebUrl": null,
      "publishedDateTime": "2021-12-21T16:00:00-08:00",
      "updatedDateTime": null,
      "provider": {
        "name": "ADVFN",
        "domain": "advfn.com",
        "images": null,
        "publishers": null,
        "authors": null
      },
      "locale": "en-us",
      "categories": [
        "news"
      ],
      "topics": [
        "AI in Autos",
        "AI"
      ]
    },
    {
      "path": "_news/2021-12-22-taking-the-world-by-simulation-the-rise-of-synthetic-data-in-ai.md",
      "title": "Taking the world by simulation: The rise of synthetic data in AI",
      "excerpt": "Would you trust AI that has been trained on synthetic data, as opposed to real-world data? You may not know it, but you probably already do.",
      "sourceUrl": null,
      "webUrl": "https://venturebeat.com/2021/12/21/taking-the-world-by-simulation-the-rise-of-synthetic-data-in-ai/",
      "originalUrl": "https://venturebeat.com/2021/12/21/taking-the-world-by-simulation-the-rise-of-synthetic-data-in-ai/",
      "featuredContent": null,
      "highlight": null,
      "heat": 87,
      "tags": null,
      "images": [
        {
          "url": "https://venturebeat.com/wp-content/uploads/2021/12/simulation-big-border.png?w=1200&strip=all",
          "width": 1200,
          "height": 600,
          "title": null,
          "attribution": null,
          "isCached": true
        }
      ],
      "content": "\r\n",
      "type": "article",
      "ampWebUrl": "https://venturebeat.com/2021/12/21/taking-the-world-by-simulation-the-rise-of-synthetic-data-in-ai/amp/",
      "cdnAmpWebUrl": "https://venturebeat-com.cdn.ampproject.org/c/s/venturebeat.com/2021/12/21/taking-the-world-by-simulation-the-rise-of-synthetic-data-in-ai/amp/",
      "publishedDateTime": "2021-12-21T15:20:00-08:00",
      "updatedDateTime": null,
      "provider": {
        "name": "VentureBeat",
        "domain": "venturebeat.com",
        "images": [
          {
            "url": "https://everyday-cc.github.io/ai/assets/images/organizations/venturebeat.com-50x50.jpg",
            "width": 50,
            "height": 50,
            "title": null,
            "attribution": null,
            "isCached": false
          }
        ],
        "publishers": null,
        "authors": null
      },
      "locale": "en-us",
      "categories": [
        "news"
      ],
      "topics": [
        "AI"
      ]
    },
    {
      "path": "_news/2021-12-22-is-artificial-intelligence-about-to-transform-the-mammogram.md",
      "title": "Is artificial intelligence about to transform the mammogram?",
      "excerpt": "An MIT researcher has devised a radical technique: an AI that can predict breast cancer. But it’s a long climb from the lab to the real world.",
      "sourceUrl": null,
      "webUrl": "https://www.washingtonpost.com/technology/2021/12/21/mammogram-artificial-intelligence-cancer-prediction/",
      "originalUrl": "https://www.washingtonpost.com/technology/2021/12/21/mammogram-artificial-intelligence-cancer-prediction/",
      "featuredContent": null,
      "highlight": null,
      "heat": null,
      "tags": null,
      "images": [
        {
          "url": "https://www.washingtonpost.com/wp-apps/imrs.php?src=https://arc-anglerfish-washpost-prod-washpost.s3.amazonaws.com/public/2K7FJNC6TMI6ZMPPZN4L44L7BY.jpg&w=1440",
          "width": 1440,
          "height": 960,
          "title": null,
          "attribution": null,
          "isCached": true
        }
      ],
      "content": "\r\n",
      "type": "article",
      "ampWebUrl": null,
      "cdnAmpWebUrl": null,
      "publishedDateTime": "2021-12-21T14:34:00-08:00",
      "updatedDateTime": null,
      "provider": {
        "name": "Washington Post",
        "domain": "washingtonpost.com",
        "images": null,
        "publishers": null,
        "authors": null
      },
      "locale": "en-us",
      "categories": [
        "news"
      ],
      "topics": [
        "AI in Healthcare",
        "AI"
      ]
    },
    {
      "path": "_news/2021-12-22-faster-safer-more-efficient-data-processing-with-edge-ai.md",
      "title": "Faster, safer, more efficient data processing with Edge AI",
      "excerpt": "The integration of AI into devices will improve the efficiency, security, and speed of data analytics. Edge AI is the future of data.",
      "sourceUrl": null,
      "webUrl": "https://venturebeat.com/2021/12/21/faster-safer-more-efficient-data-processing-with-edge-ai/",
      "originalUrl": "https://venturebeat.com/2021/12/21/faster-safer-more-efficient-data-processing-with-edge-ai/",
      "featuredContent": null,
      "highlight": null,
      "heat": 89,
      "tags": null,
      "images": [
        {
          "url": "https://venturebeat.com/wp-content/uploads/2021/12/GettyImages-1277718299.jpg?w=1200&strip=all",
          "width": 1200,
          "height": 675,
          "title": null,
          "attribution": null,
          "isCached": true
        }
      ],
      "content": "\r\n",
      "type": "article",
      "ampWebUrl": "https://venturebeat.com/2021/12/21/faster-safer-more-efficient-data-processing-with-edge-ai/amp/",
      "cdnAmpWebUrl": "https://venturebeat-com.cdn.ampproject.org/c/s/venturebeat.com/2021/12/21/faster-safer-more-efficient-data-processing-with-edge-ai/amp/",
      "publishedDateTime": "2021-12-21T14:20:00-08:00",
      "updatedDateTime": null,
      "provider": {
        "name": "VentureBeat",
        "domain": "venturebeat.com",
        "images": [
          {
            "url": "https://everyday-cc.github.io/ai/assets/images/organizations/venturebeat.com-50x50.jpg",
            "width": 50,
            "height": 50,
            "title": null,
            "attribution": null,
            "isCached": false
          }
        ],
        "publishers": null,
        "authors": null
      },
      "locale": "en-us",
      "categories": [
        "news"
      ],
      "topics": [
        "AI",
        "AI Hardware"
      ]
    },
    {
      "path": "_news/2021-12-22-azure-space-introduces-azure-orbital-in-preview-and-new-geospatial-capabilities.md",
      "title": "Azure Space Introduces Azure Orbital in Preview and New Geospatial Capabilities",
      "excerpt": "Microsoft recently announced new satellite connectivity and geospatial capabilities for Azure Space. The cloud provider introduced the preview of Azure Orbital, a ground station as-a-service that provides communication and control of satellites,",
      "sourceUrl": null,
      "webUrl": "https://www.infoq.com/news/2021/12/azure-space-orbital/",
      "originalUrl": "https://www.infoq.com/news/2021/12/azure-space-orbital/",
      "featuredContent": null,
      "highlight": null,
      "heat": null,
      "tags": null,
      "images": [
        {
          "url": "https://res.infoq.com/news/2021/12/azure-space-orbital/en/headerimage/generatedHeaderImage-1639513471207.jpg",
          "width": 1200,
          "height": 630,
          "title": null,
          "attribution": null,
          "isCached": true
        }
      ],
      "content": "\r\n",
      "type": "article",
      "ampWebUrl": null,
      "cdnAmpWebUrl": null,
      "publishedDateTime": "2021-12-21T13:24:00-08:00",
      "updatedDateTime": null,
      "provider": {
        "name": "InfoQ",
        "domain": "infoq.com",
        "images": null,
        "publishers": null,
        "authors": null
      },
      "locale": "en-us",
      "categories": [
        "news"
      ],
      "topics": [
        "Microsoft AI",
        "AI"
      ]
    },
    {
      "path": "_news/2021-12-22-2022-technology-trend-review-part-two-ai-and-graphs.md",
      "title": "2022 technology trend review, part two: AI and graphs",
      "excerpt": "AI and graphs have a few things in common: they are multi-faceted, ubiquitous in their applications, and seeing rapid growth in the 2020s.",
      "sourceUrl": null,
      "webUrl": "https://www.zdnet.com/article/2022-technology-trend-review-part-two-ai-and-graphs/",
      "originalUrl": "https://www.zdnet.com/article/2022-technology-trend-review-part-two-ai-and-graphs/",
      "featuredContent": null,
      "highlight": null,
      "heat": 99,
      "tags": null,
      "images": [
        {
          "url": "https://www.zdnet.com/a/img/resize/b81aba36b92e149af0df467e70c7854b49258446/2021/11/02/900a38bb-71d8-4ccf-bef9-0916bce3d2ac/shutterstock-1948106629.jpg?width=1200&fit=bounds&auto=webp",
          "width": 1200,
          "height": 675,
          "title": null,
          "attribution": null,
          "isCached": true
        }
      ],
      "content": "\r\n",
      "type": "article",
      "ampWebUrl": "https://www.zdnet.com/google-amp/article/2022-technology-trend-review-part-two-ai-and-graphs/",
      "cdnAmpWebUrl": "https://www-zdnet-com.cdn.ampproject.org/c/s/www.zdnet.com/google-amp/article/2022-technology-trend-review-part-two-ai-and-graphs/",
      "publishedDateTime": "2021-12-21T12:34:00-08:00",
      "updatedDateTime": null,
      "provider": {
        "name": "ZDNet",
        "domain": "zdnet.com",
        "images": [
          {
            "url": "https://everyday-cc.github.io/ai/assets/images/organizations/zdnet.com-50x50.jpg",
            "width": 50,
            "height": 50,
            "title": null,
            "attribution": null,
            "isCached": false
          }
        ],
        "publishers": null,
        "authors": null
      },
      "locale": "en-us",
      "categories": [
        "news"
      ],
      "topics": [
        "AI Hardware",
        "AI"
      ]
    },
    {
      "path": "_news/2021-12-22-sait-using-autonomous-robots-to-clean-main-campus.md",
      "title": "SAIT using autonomous robots to clean main campus",
      "excerpt": "SAIT has started using autonomous robots to clean the floors at its main campus. The robots are from Brain Corp, an artificial intelligence (AI) company, and contracted to SAIT for use through Calgary-based Bee Clean,",
      "sourceUrl": null,
      "webUrl": "https://calgary.ctvnews.ca/sait-using-autonomous-robots-to-clean-main-campus-1.5715514",
      "originalUrl": "https://calgary.ctvnews.ca/sait-using-autonomous-robots-to-clean-main-campus-1.5715514",
      "featuredContent": null,
      "highlight": null,
      "heat": 74,
      "tags": null,
      "images": [
        {
          "url": "https://beta.ctvnews.ca/local/calgary/2021/12/21/1_5715514/_jcr_content/root/responsivegrid/image.coreimg.jpg",
          "width": 1020,
          "height": 576,
          "title": null,
          "attribution": null,
          "isCached": true
        }
      ],
      "content": "\r\n",
      "type": "article",
      "ampWebUrl": "https://beta.ctvnews.ca/local/calgary/2021/12/21/1_5715514.amp.html",
      "cdnAmpWebUrl": "https://beta-ctvnews-ca.cdn.ampproject.org/c/s/beta.ctvnews.ca/local/calgary/2021/12/21/1_5715514.amp.html",
      "publishedDateTime": "2021-12-21T12:20:00-08:00",
      "updatedDateTime": null,
      "provider": {
        "name": "CTV News",
        "domain": "ctvnews.ca",
        "images": null,
        "publishers": null,
        "authors": null
      },
      "locale": "en-us",
      "categories": [
        "news"
      ],
      "topics": [
        "AI in Robotics",
        "AI"
      ]
    },
    {
      "path": "_news/2021-12-22-50-global-hubs-for-top-ai-talent.md",
      "title": "50 Global Hubs for Top AI Talent",
      "excerpt": "As AI expands into more and more facets of our lives, there is also more scrutiny on who is developing it. Building ethical AI that works for everyone will require a diverse workforce that brings a broad range of perspectives.",
      "sourceUrl": null,
      "webUrl": "https://hbr.org/2021/12/50-global-hubs-for-top-ai-talent",
      "originalUrl": "https://hbr.org/2021/12/50-global-hubs-for-top-ai-talent",
      "featuredContent": null,
      "highlight": null,
      "heat": 177,
      "tags": null,
      "images": [
        {
          "url": "https://hbr.org/resources/images/article_assets/2021/11/Dec21_07_brian-kostiuk_luke-stackpoole_unsplash_2.jpg",
          "width": 2000,
          "height": 1125,
          "title": null,
          "attribution": null,
          "isCached": true
        }
      ],
      "content": "\r\n",
      "type": "article",
      "ampWebUrl": "https://hbr.org/amp/2021/12/50-global-hubs-for-top-ai-talent",
      "cdnAmpWebUrl": "https://hbr-org.cdn.ampproject.org/c/s/hbr.org/amp/2021/12/50-global-hubs-for-top-ai-talent",
      "publishedDateTime": "2021-12-21T11:14:00-08:00",
      "updatedDateTime": null,
      "provider": {
        "name": "Harvard Business Review",
        "domain": "hbr.org",
        "images": null,
        "publishers": null,
        "authors": null
      },
      "locale": "en-us",
      "categories": [
        "news"
      ],
      "topics": [
        "AI"
      ]
    },
    {
      "path": "_news/2021-12-22-face-detection-in-untrained-deep-neural-networks.md",
      "title": "Face detection in untrained deep neural networks",
      "excerpt": "Researchers have found that higher visual cognitive functions can arise spontaneously in untrained neural networks. A KAIST research team led by Professor Se-Bum Paik from the Department of Bio and Brain Engineering has shown that visual selectivity of facial images can arise even in completely untrained deep neural networks.",
      "sourceUrl": null,
      "webUrl": "https://www.eurekalert.org/news-releases/938633",
      "originalUrl": "https://www.eurekalert.org/news-releases/938633",
      "featuredContent": null,
      "highlight": null,
      "heat": null,
      "tags": null,
      "images": [
        {
          "url": "https://earimediaprodweb.azurewebsites.net/Api/v1/Multimedia/287aa929-bfb7-4958-9f9f-184912fa866c/Rendition/low-res/Content/Public",
          "width": 700,
          "height": 336,
          "title": null,
          "attribution": null,
          "isCached": true
        }
      ],
      "content": "\r\n",
      "type": "article",
      "ampWebUrl": null,
      "cdnAmpWebUrl": null,
      "publishedDateTime": "2021-12-21T09:13:00-08:00",
      "updatedDateTime": null,
      "provider": {
        "name": "EurekAlert!",
        "domain": "eurekalert.org",
        "images": null,
        "publishers": null,
        "authors": null
      },
      "locale": "en-us",
      "categories": [
        "news"
      ],
      "topics": [
        "Machine Learning",
        "AI"
      ]
    },
    {
      "path": "_news/2021-12-22-omicron-looms-large-over-healthcare-workers-and-ai-can-help.md",
      "title": "Omicron Looms Large Over Healthcare Workers, And AI Can Help",
      "excerpt": "As COVID-19 vaccination rates rise and the U.S. and other countries gain more knowledge of the virus, decision-makers must adjust their policies to better prepare for omicron and future variants. Of the more than 240 million people confirmed to have contracted COVID-19,",
      "sourceUrl": null,
      "webUrl": "https://www.nasdaq.com/articles/omicron-looms-large-over-healthcare-workers-and-ai-can-help",
      "originalUrl": "https://www.nasdaq.com/articles/omicron-looms-large-over-healthcare-workers-and-ai-can-help",
      "featuredContent": null,
      "highlight": null,
      "heat": 84,
      "tags": null,
      "images": null,
      "content": "\r\n",
      "type": "article",
      "ampWebUrl": "https://www.nasdaq.com/articles/omicron-looms-large-over-healthcare-workers-and-ai-can-help?amp",
      "cdnAmpWebUrl": "https://www-nasdaq-com.cdn.ampproject.org/c/s/www.nasdaq.com/articles/omicron-looms-large-over-healthcare-workers-and-ai-can-help?amp",
      "publishedDateTime": "2021-12-21T09:01:00-08:00",
      "updatedDateTime": null,
      "provider": {
        "name": "Nasdaq",
        "domain": "nasdaq.com",
        "images": null,
        "publishers": null,
        "authors": null
      },
      "locale": "en-us",
      "categories": [
        "news"
      ],
      "topics": [
        "AI in Healthcare",
        "AI"
      ]
    },
    {
      "path": "_news/2021-12-22-hosting-infrastructure-services-market-size-2021-global-industry-share-top-players-opportunities-and-forecast-to-2029.md",
      "title": "Hosting Infrastructure Services Market Size 2021 Global Industry Share, Top Players, Opportunities And Forecast To 2029",
      "excerpt": "The global hosting infrastructure services market is estimated to reach a value of US 12 billion in 2019 up from US 11 billion in 2018 according to a recently published report by Future Market Insights FMI Gains remain underpinned by",
      "sourceUrl": null,
      "webUrl": "https://www.openpr.com/news/2506997/hosting-infrastructure-services-market-size-2021-global",
      "originalUrl": "https://www.openpr.com/news/2506997/hosting-infrastructure-services-market-size-2021-global",
      "featuredContent": null,
      "highlight": null,
      "heat": null,
      "tags": null,
      "images": null,
      "content": "\r\n",
      "type": "article",
      "ampWebUrl": "https://www.openpr.com/amp/2506997/hosting-infrastructure-services-market-size-2021-global",
      "cdnAmpWebUrl": "https://www-openpr-com.cdn.ampproject.org/c/s/www.openpr.com/amp/2506997/hosting-infrastructure-services-market-size-2021-global",
      "publishedDateTime": "2021-12-21T08:52:00-08:00",
      "updatedDateTime": null,
      "provider": {
        "name": "openpr.com",
        "domain": "openpr.com",
        "images": null,
        "publishers": null,
        "authors": null
      },
      "locale": "en-us",
      "categories": [
        "news"
      ],
      "topics": [
        "AI in Finance",
        "AI"
      ]
    }
  ],
  "nextPage": 27
}