{
  "page": 56,
  "value": [
    {
      "path": "_news/2022-02-23-speech-graphics-raises-7m-for-lip-synced-facial-animation.md",
      "title": "Speech Graphics raises $7M for lip-synced facial animation",
      "excerpt": "Speech Graphics has raised $7 million in funding to build its audio-driven facial animation technology. It is dubbing, using AI.",
      "sourceUrl": null,
      "webUrl": "https://venturebeat.com/2022/02/23/speech-graphics-raises-7m-for-audio-driven-facial-animation/",
      "originalUrl": "https://venturebeat.com/2022/02/23/speech-graphics-raises-7m-for-audio-driven-facial-animation/",
      "featuredContent": null,
      "highlight": null,
      "heat": 89,
      "tags": null,
      "images": [
        {
          "url": "https://venturebeat.com/wp-content/uploads/2022/02/speech.jpg?w=1200&strip=all",
          "width": 1200,
          "height": 652,
          "title": null,
          "attribution": null,
          "isCached": true
        }
      ],
      "content": "\r\n",
      "type": "article",
      "ampWebUrl": "https://venturebeat.com/2022/02/23/speech-graphics-raises-7m-for-audio-driven-facial-animation/amp/",
      "cdnAmpWebUrl": "https://venturebeat-com.cdn.ampproject.org/c/s/venturebeat.com/2022/02/23/speech-graphics-raises-7m-for-audio-driven-facial-animation/amp/",
      "publishedDateTime": "2022-02-23T06:00:00-08:00",
      "updatedDateTime": null,
      "provider": {
        "name": "VentureBeat",
        "domain": "venturebeat.com",
        "images": [
          {
            "url": "https://everyday-cc.github.io/ai/assets/images/organizations/venturebeat.com-50x50.jpg",
            "width": 50,
            "height": 50,
            "title": null,
            "attribution": null,
            "isCached": false
          }
        ],
        "publishers": null,
        "authors": null
      },
      "locale": "en-us",
      "categories": [
        "news"
      ],
      "topics": [
        "Natural Language Processing",
        "AI"
      ]
    },
    {
      "path": "_news/2022-02-23-artificial-intelligence-and-robotics-could-be-growth-area-for-bradford-but-there-are-still-gaps-in-tech-inequality.md",
      "title": "Artificial intelligence and robotics could be 'growth area' for Bradford - but there are still gaps in tech inequality",
      "excerpt": "ARTIFICIAL Intelligence and robotics could \"major growth areas\" for Bradford in the coming years - a meeting has heard.",
      "sourceUrl": null,
      "webUrl": "https://www.thetelegraphandargus.co.uk/news/19943900.artificial-intelligence-robotics-growth-area-bradford---still-gaps-tech-inequality/",
      "originalUrl": "https://www.thetelegraphandargus.co.uk/news/19943900.artificial-intelligence-robotics-growth-area-bradford---still-gaps-tech-inequality/",
      "featuredContent": null,
      "highlight": null,
      "heat": 75,
      "tags": null,
      "images": [
        {
          "url": "https://www.thetelegraphandargus.co.uk/resources/images/13502282/?type=responsive-gallery",
          "width": 650,
          "height": 433,
          "title": null,
          "attribution": null,
          "isCached": true
        }
      ],
      "content": "\r\n",
      "type": "article",
      "ampWebUrl": "https://www.thetelegraphandargus.co.uk/news/19943900.amp/",
      "cdnAmpWebUrl": "https://www-thetelegraphandargus-co-uk.cdn.ampproject.org/c/s/www.thetelegraphandargus.co.uk/news/19943900.amp/",
      "publishedDateTime": "2022-02-23T05:57:00-08:00",
      "updatedDateTime": null,
      "provider": {
        "name": "Telegraph & Argus",
        "domain": "thetelegraphandargus.co.uk",
        "images": null,
        "publishers": null,
        "authors": null
      },
      "locale": "en-us",
      "categories": [
        "news"
      ],
      "topics": [
        "AI in Robotics",
        "AI"
      ]
    },
    {
      "path": "_news/2022-02-23-how-a-financial-planner-went-from-broke-to-generating-85-million.md",
      "title": "How A Financial Planner Went From Broke To Generating $8.5 Million",
      "excerpt": "Failure is a great teacher. When a financial manager went into debt, she took her own advice to manage her business, wealth and investments better.",
      "sourceUrl": null,
      "webUrl": "https://www.forbes.com/sites/geristengel/2022/02/23/how-a-financial-planner-went-from-broke-to-generating-85-million/",
      "originalUrl": "https://www.forbes.com/sites/geristengel/2022/02/23/how-a-financial-planner-went-from-broke-to-generating-85-million/",
      "featuredContent": null,
      "highlight": null,
      "heat": 74,
      "tags": null,
      "images": [
        {
          "url": "https://imageio.forbes.com/specials-images/imageserve/62159857d3e152c3f3c0952c/0x0.jpg?format=jpg&width=1200&fit=bounds",
          "width": 960,
          "height": 720,
          "title": null,
          "attribution": null,
          "isCached": true
        }
      ],
      "content": "\r\n",
      "type": "article",
      "ampWebUrl": "https://www.forbes.com/sites/geristengel/2022/02/23/how-a-financial-planner-went-from-broke-to-generating-85-million/amp/",
      "cdnAmpWebUrl": "https://www-forbes-com.cdn.ampproject.org/c/s/www.forbes.com/sites/geristengel/2022/02/23/how-a-financial-planner-went-from-broke-to-generating-85-million/amp/",
      "publishedDateTime": "2022-02-23T03:00:00-08:00",
      "updatedDateTime": null,
      "provider": {
        "name": "Forbes",
        "domain": "forbes.com",
        "images": [
          {
            "url": "https://everyday-cc.github.io/ai/assets/images/organizations/forbes.com-50x50.jpg",
            "width": 50,
            "height": 50,
            "title": null,
            "attribution": null,
            "isCached": false
          }
        ],
        "publishers": null,
        "authors": null
      },
      "locale": "en-us",
      "categories": [
        "news"
      ],
      "topics": [
        "AI in Finance",
        "AI"
      ]
    },
    {
      "path": "_news/2022-02-23-digital-twins-ai-ml-transforming-the-fintech-landscape.md",
      "title": "Digital Twins: AI & ML Transforming the Fintech Landscape",
      "excerpt": "As emerging technologies of AI and ML get weaved into the fintech fabric, the industry will have to prep up to address an avalanche of new use-cases",
      "sourceUrl": null,
      "webUrl": "https://www.entrepreneur.com/article/420077",
      "originalUrl": "https://www.entrepreneur.com/article/420077",
      "featuredContent": null,
      "highlight": null,
      "heat": 136,
      "tags": null,
      "images": [
        {
          "url": "https://assets.entrepreneur.com/content/3x2/2000/1645607608-MyPost10.jpg",
          "width": 2000,
          "height": 1333,
          "title": null,
          "attribution": null,
          "isCached": true
        }
      ],
      "content": "\r\n",
      "type": "article",
      "ampWebUrl": null,
      "cdnAmpWebUrl": null,
      "publishedDateTime": "2022-02-23T01:15:00-08:00",
      "updatedDateTime": null,
      "provider": {
        "name": "Entrepreneur",
        "domain": "entrepreneur.com",
        "images": [
          {
            "url": "https://everyday-cc.github.io/ai/assets/images/organizations/entrepreneur.com-50x50.jpg",
            "width": 50,
            "height": 50,
            "title": null,
            "attribution": null,
            "isCached": false
          }
        ],
        "publishers": null,
        "authors": null
      },
      "locale": "en-us",
      "categories": [
        "news"
      ],
      "topics": [
        "AI in Finance",
        "AI",
        "Machine Learning"
      ]
    },
    {
      "path": "_news/2022-02-23-court-rules-that-waymo-can-keep-its-robotaxi-emergency-protocols-a-secret.md",
      "title": "Court rules that Waymo can keep its robotaxi emergency protocols a secret",
      "excerpt": "The California Superior Court in Sacramento has ruled in favor of Waymo, allowing the company to keep specific details about its autonomous vehicle technology a secret. Waymo won the case against the California Department of Motor Vehicles,",
      "sourceUrl": null,
      "webUrl": "https://www.engadget.com/court-rules-waymo-can-keep-robotaxi-emergency-protocols-secret-084641836.html",
      "originalUrl": "https://www.engadget.com/court-rules-waymo-can-keep-robotaxi-emergency-protocols-secret-084641836.html",
      "featuredContent": null,
      "highlight": null,
      "heat": 168,
      "tags": null,
      "images": [
        {
          "url": "https://s.yimg.com/os/creatr-uploaded-images/2022-02/67df5d70-947c-11ec-aaf7-a06e955e8824",
          "width": 1600,
          "height": 1003,
          "title": null,
          "attribution": null,
          "isCached": true
        }
      ],
      "content": "\r\n",
      "type": "article",
      "ampWebUrl": null,
      "cdnAmpWebUrl": null,
      "publishedDateTime": "2022-02-23T00:59:00-08:00",
      "updatedDateTime": null,
      "provider": {
        "name": "Engadget",
        "domain": "engadget.com",
        "images": [
          {
            "url": "/assets/images/organizations/engadget.com-50x50.jpg",
            "width": 50,
            "height": 50,
            "title": null,
            "attribution": null,
            "isCached": false
          }
        ],
        "publishers": null,
        "authors": null
      },
      "locale": "en-us",
      "categories": [
        "news"
      ],
      "topics": [
        "AI",
        "AI in Autos"
      ]
    },
    {
      "path": "_news/2022-02-23-maple-leaf-sports-entertainment-and-aws-team-up-to-transform-experiences-for-canadian-sports-fans.md",
      "title": "Maple Leaf Sports & Entertainment and AWS Team Up to Transform Experiences for Canadian Sports Fans",
      "excerpt": "MLSE aims to offer its teams new AWS-powered insights to further improve the caliber of gameplay. Using Amazon Rekognition (AWS&CloseCurlyQuote;s service for automated image and video analysis) and Amazon Kinesis (AWS&CloseCurlyQuote;s service for easily ...",
      "sourceUrl": null,
      "webUrl": "https://stockhouse.com/news/press-releases/2022/02/23/maple-leaf-sports-entertainment-and-aws-team-up-to-transform-experiences-for",
      "originalUrl": "https://stockhouse.com/news/press-releases/2022/02/23/maple-leaf-sports-entertainment-and-aws-team-up-to-transform-experiences-for",
      "featuredContent": null,
      "highlight": null,
      "heat": null,
      "tags": null,
      "images": null,
      "content": "\r\n",
      "type": "article",
      "ampWebUrl": null,
      "cdnAmpWebUrl": null,
      "publishedDateTime": "2022-02-23T00:02:00-08:00",
      "updatedDateTime": null,
      "provider": {
        "name": "Stockhouse",
        "domain": "stockhouse.com",
        "images": null,
        "publishers": null,
        "authors": null
      },
      "locale": "en-us",
      "categories": [
        "news"
      ],
      "topics": [
        "AWS AI",
        "AI"
      ]
    },
    {
      "path": "_news/2022-02-23-cyclerion-therapeutics-and-ariana-pharma-announce-an-artificial-intelligence-driven-precision-medicine-collaboration.md",
      "title": "Cyclerion Therapeutics and Ariana Pharma Announce an Artificial Intelligence-driven Precision Medicine Collaboration",
      "excerpt": "Ariana Pharma's proprietary KEM(R) (Knowledge Extraction and Management) eXplainable Artificial Intelligence (xAI ... who may benefit most from the therapy, by identifying patient-selection ...",
      "sourceUrl": null,
      "webUrl": "https://www.marketwatch.com/press-release/cyclerion-therapeutics-and-ariana-pharma-announce-an-artificial-intelligence-driven-precision-medicine-collaboration-2022-02-23",
      "originalUrl": "https://www.marketwatch.com/press-release/cyclerion-therapeutics-and-ariana-pharma-announce-an-artificial-intelligence-driven-precision-medicine-collaboration-2022-02-23",
      "featuredContent": null,
      "highlight": null,
      "heat": null,
      "tags": null,
      "images": [
        {
          "url": "https://mw3.wsj.net/mw5/content/logos/mw_logo_social.png",
          "width": 1200,
          "height": 630,
          "title": null,
          "attribution": null,
          "isCached": true
        }
      ],
      "content": "\r\n",
      "type": "article",
      "ampWebUrl": null,
      "cdnAmpWebUrl": null,
      "publishedDateTime": "2022-02-23T00:00:00-08:00",
      "updatedDateTime": null,
      "provider": {
        "name": "MarketWatch",
        "domain": "marketwatch.com",
        "images": [
          {
            "url": "https://everyday-cc.github.io/ai/assets/images/organizations/marketwatch.com-50x50.jpg",
            "width": 50,
            "height": 50,
            "title": null,
            "attribution": null,
            "isCached": false
          }
        ],
        "publishers": null,
        "authors": null
      },
      "locale": "en-us",
      "categories": [
        "news"
      ],
      "topics": [
        "AI in Healthcare",
        "AI"
      ]
    },
    {
      "path": "_news/2022-02-23-exponentiaai-raises-additional-funding-from-amit-midha-and-technog-solutions.md",
      "title": "Exponentia.ai raises additional funding from Amit Midha and Technog Solutions",
      "excerpt": "Exponentia.ai has announced that it has raised funding from Investors - Amit Midha, President - Dell Technologies and Technog Solutions.",
      "sourceUrl": null,
      "webUrl": "https://www.business-standard.com/content/press-releases-ani/exponentia-ai-raises-additional-funding-from-amit-midha-and-technog-solutions-122022300687_1.html",
      "originalUrl": "https://www.business-standard.com/content/press-releases-ani/exponentia-ai-raises-additional-funding-from-amit-midha-and-technog-solutions-122022300687_1.html",
      "featuredContent": null,
      "highlight": null,
      "heat": 76,
      "tags": null,
      "images": [
        {
          "url": "https://bsmedia.business-standard.com/_media/bs/img/article/2022-02/23/full/20220223124931.jpg",
          "width": 600,
          "height": 450,
          "title": null,
          "attribution": null,
          "isCached": true
        }
      ],
      "content": "\r\n",
      "type": "article",
      "ampWebUrl": "https://wap.business-standard.com/content-amp/press-releases-ani/exponentia-ai-raises-additional-funding-from-amit-midha-and-technog-solutions-122022300687_1.html",
      "cdnAmpWebUrl": "https://wap-business--standard-com.cdn.ampproject.org/c/s/wap.business-standard.com/content-amp/press-releases-ani/exponentia-ai-raises-additional-funding-from-amit-midha-and-technog-solutions-122022300687_1.html",
      "publishedDateTime": "2022-02-23T00:00:00-08:00",
      "updatedDateTime": null,
      "provider": {
        "name": "Business Standard",
        "domain": "business-standard.com",
        "images": null,
        "publishers": null,
        "authors": null
      },
      "locale": "en-us",
      "categories": [
        "news"
      ],
      "topics": [
        "Microsoft AI",
        "AI"
      ]
    },
    {
      "path": "_news/2022-02-23-exponentiaai-raises-additional-funding-from-mr-amit-midha-and-technog-solutions.md",
      "title": "Exponentia.ai raises additional funding from Mr. Amit Midha and Technog Solutions",
      "excerpt": "Exponentia.ai has announced that it has raised funding from Investors - Mr. Amit Midha, President - Dell Technologies and Technog Solutions. The funds will be used to strengthen Exponentia's offerings in the AI space and expand to new geographies.",
      "sourceUrl": null,
      "webUrl": "https://www.tmcnet.com/usubmit/2022/02/23/9550279.htm",
      "originalUrl": "https://www.tmcnet.com/usubmit/2022/02/23/9550279.htm",
      "featuredContent": null,
      "highlight": null,
      "heat": null,
      "tags": null,
      "images": [
        {
          "url": "https://mma.prnewswire.com/media/1752365/ramendra_shukla.jpg",
          "width": 400,
          "height": 391,
          "title": null,
          "attribution": null,
          "isCached": true
        }
      ],
      "content": "\r\n",
      "type": "article",
      "ampWebUrl": null,
      "cdnAmpWebUrl": null,
      "publishedDateTime": "2022-02-22T22:32:00-08:00",
      "updatedDateTime": null,
      "provider": {
        "name": "TMCnet",
        "domain": "tmcnet.com",
        "images": null,
        "publishers": null,
        "authors": null
      },
      "locale": "en-us",
      "categories": [
        "news"
      ],
      "topics": [
        "Microsoft AI",
        "AI"
      ]
    },
    {
      "path": "_news/2022-02-23-microsofts-new-singularity-ai-system-might-have-100000-gpus.md",
      "title": "Microsoft’s New ‘Singularity’ AI System Might Have 100,000+ GPUs",
      "excerpt": "Microsoft's research teams are working on Singularity, a new infrastructre to manage AI and deep learning workloads.",
      "sourceUrl": null,
      "webUrl": "https://fossbytes.com/microsoft-singularity-ai-gpu/",
      "originalUrl": "https://fossbytes.com/microsoft-singularity-ai-gpu/",
      "featuredContent": null,
      "highlight": null,
      "heat": 94,
      "tags": null,
      "images": [
        {
          "url": "https://fossbytes.com/wp-content/uploads/2022/02/microsoft-ai.jpg",
          "width": 1200,
          "height": 675,
          "title": null,
          "attribution": null,
          "isCached": true
        }
      ],
      "content": "\r\n",
      "type": "article",
      "ampWebUrl": "https://fossbytes.com/microsoft-singularity-ai-gpu/amp/",
      "cdnAmpWebUrl": "https://fossbytes-com.cdn.ampproject.org/c/s/fossbytes.com/microsoft-singularity-ai-gpu/amp/",
      "publishedDateTime": "2022-02-22T21:44:00-08:00",
      "updatedDateTime": null,
      "provider": {
        "name": "Foss Bytes",
        "domain": "fossbytes.com",
        "images": null,
        "publishers": null,
        "authors": null
      },
      "locale": "en-us",
      "categories": [
        "news"
      ],
      "topics": [
        "Microsoft AI",
        "AI"
      ]
    },
    {
      "path": "_news/2022-02-23-artificial-intelligence-and-robotics-could-be-growth-are-for-bradford-but-there-are-still-gaps-in-tech-inequality.md",
      "title": "Artificial intelligence and robotics could be 'growth are' for Bradford - but there are still gaps in tech inequality",
      "excerpt": "ARTIFICIAL Intelligence and robotics could \"major growth areas\" for Bradford in the coming years - a meeting has heard.",
      "sourceUrl": null,
      "webUrl": "https://www.thetelegraphandargus.co.uk/news/19943900.artificial-intelligence-robotics-growth-are-bradford---still-gaps-tech-inequality/",
      "originalUrl": "https://www.thetelegraphandargus.co.uk/news/19943900.artificial-intelligence-robotics-growth-are-bradford---still-gaps-tech-inequality/",
      "featuredContent": null,
      "highlight": null,
      "heat": 86,
      "tags": null,
      "images": [
        {
          "url": "https://www.thetelegraphandargus.co.uk/resources/images/13502282/?type=responsive-gallery",
          "width": 650,
          "height": 433,
          "title": null,
          "attribution": null,
          "isCached": true
        }
      ],
      "content": "\r\n",
      "type": "article",
      "ampWebUrl": "https://www.thetelegraphandargus.co.uk/news/19943900.amp/",
      "cdnAmpWebUrl": "https://www-thetelegraphandargus-co-uk.cdn.ampproject.org/c/s/www.thetelegraphandargus.co.uk/news/19943900.amp/",
      "publishedDateTime": "2022-02-22T21:00:00-08:00",
      "updatedDateTime": null,
      "provider": {
        "name": "Telegraph & Argus",
        "domain": "thetelegraphandargus.co.uk",
        "images": null,
        "publishers": null,
        "authors": null
      },
      "locale": "en-us",
      "categories": [
        "news"
      ],
      "topics": [
        "AI in Robotics",
        "AI"
      ]
    },
    {
      "path": "_news/2022-02-23-irs-doesnt-completely-scrap-facial-recognition-just-makes-it-optional.md",
      "title": "IRS doesn't completely scrap facial recognition, just makes it optional",
      "excerpt": "Folks setting up an online IRS account will be given the choice of providing biometric data, or speaking with a human agent in a video call, to authenticate. Those who are comfortable with facial recognition can submit a selfie,",
      "sourceUrl": null,
      "webUrl": "https://www.theregister.com/2022/02/23/irs_facial_deletion/",
      "originalUrl": "https://www.theregister.com/2022/02/23/irs_facial_deletion/",
      "featuredContent": null,
      "highlight": null,
      "heat": 99,
      "tags": null,
      "images": [
        {
          "url": "https://regmedia.co.uk/2020/01/17/shutterstock_facial_recognition.jpg",
          "width": 1000,
          "height": 527,
          "title": null,
          "attribution": null,
          "isCached": true
        }
      ],
      "content": "\r\n",
      "type": "article",
      "ampWebUrl": "https://www.theregister.com/AMP/2022/02/23/irs_facial_deletion/",
      "cdnAmpWebUrl": "https://www-theregister-com.cdn.ampproject.org/c/s/www.theregister.com/AMP/2022/02/23/irs_facial_deletion/",
      "publishedDateTime": "2022-02-22T20:19:00-08:00",
      "updatedDateTime": null,
      "provider": {
        "name": "theregister",
        "domain": "theregister.com",
        "images": null,
        "publishers": null,
        "authors": null
      },
      "locale": "en-us",
      "categories": [
        "news"
      ],
      "topics": [
        "Computer Vision",
        "AI"
      ]
    },
    {
      "path": "_news/2022-02-23-control-formality-in-machine-translated-text-using-amazon-translate.md",
      "title": "Control formality in machine translated text using Amazon Translate",
      "excerpt": "Amazon Translate&nbsp;is a neural machine translation service that delivers fast, high-quality, affordable, and customizable language translation. Amazon Translate now supports formality customization. This feature allows you to customize the level of formality in your translation output. At the time",
      "sourceUrl": null,
      "webUrl": "https://aws.amazon.com/blogs/machine-learning/control-formality-in-machine-translated-text-using-amazon-translate/",
      "originalUrl": "https://aws.amazon.com/blogs/machine-learning/control-formality-in-machine-translated-text-using-amazon-translate/",
      "featuredContent": null,
      "highlight": null,
      "heat": 126,
      "tags": null,
      "images": [
        {
          "url": "https://d2908q01vomqb2.cloudfront.net/827bfc458708f0b442009c9c9836f7e4b65557fb/2020/06/03/Blog-Post_thumbnail.png",
          "width": 768,
          "height": 385,
          "title": null,
          "attribution": null,
          "isCached": true
        }
      ],
      "content": "\r\n",
      "type": "article",
      "ampWebUrl": null,
      "cdnAmpWebUrl": null,
      "publishedDateTime": "2022-02-22T19:45:15-08:00",
      "updatedDateTime": null,
      "provider": {
        "name": "AWS",
        "domain": "aws.amazon.com",
        "images": [
          {
            "url": "https://everyday-cc.github.io/ai/assets/images/organizations/aws.amazon.com-50x50.jpg",
            "width": 50,
            "height": 50,
            "title": null,
            "attribution": null,
            "isCached": false
          }
        ],
        "publishers": null,
        "authors": null
      },
      "locale": "en-us",
      "categories": [
        "news"
      ],
      "topics": [
        "AI",
        "AWS AI",
        "Natural Language Processing"
      ]
    },
    {
      "path": "_news/2022-02-23-semiconductor-watch-list-key-chip-ingredients-at-risk-in-ukraine-conflict.md",
      "title": "Semiconductor Watch List: Key Chip Ingredients At Risk in Ukraine Conflict",
      "excerpt": "The alarming prospect of war on the European continent -- in what would be the largest scale conflict since the Yugoslav wars -- has roiled the markets,” wrote Real Money’s Kevin Curran recently. “Meanwhile,",
      "sourceUrl": null,
      "webUrl": "https://www.thestreet.com/investing/semiconductor-watch-list-key-chip-ingredients-at-risk-in-ukraine-conflict",
      "originalUrl": "https://www.thestreet.com/investing/semiconductor-watch-list-key-chip-ingredients-at-risk-in-ukraine-conflict",
      "featuredContent": null,
      "highlight": null,
      "heat": 72,
      "tags": null,
      "images": [
        {
          "url": "https://www.thestreet.com/.image/c_fill%2Ccs_srgb%2Cfl_progressive%2Ch_400%2Cq_auto:good%2Cw_620/MTc5MzkyMTc5NTIzODIyOTI1/stock-trader-distressed.jpg",
          "width": 620,
          "height": 400,
          "title": null,
          "attribution": null,
          "isCached": true
        }
      ],
      "content": "\r\n",
      "type": "article",
      "ampWebUrl": "https://www.thestreet.com/.amp/investing/semiconductor-watch-list-key-chip-ingredients-at-risk-in-ukraine-conflict",
      "cdnAmpWebUrl": "https://www-thestreet-com.cdn.ampproject.org/c/s/www.thestreet.com/.amp/investing/semiconductor-watch-list-key-chip-ingredients-at-risk-in-ukraine-conflict",
      "publishedDateTime": "2022-02-22T18:05:00-08:00",
      "updatedDateTime": null,
      "provider": {
        "name": "TheStreet.com",
        "domain": "thestreet.com",
        "images": null,
        "publishers": null,
        "authors": null
      },
      "locale": "en-us",
      "categories": [
        "news"
      ],
      "topics": [
        "AI Hardware",
        "AI"
      ]
    },
    {
      "path": "_news/2022-02-23-eca-to-inaugurate-africas-1st-ai-research-centre-in-brazzaville-congo.md",
      "title": "ECA to Inaugurate Africa’s 1st AI Research Centre in Brazzaville Congo",
      "excerpt": "Addis Ababa, February 23/2022 /ENA/ The Economic Commission for Africa (ECA) is set to launch Africa’s first Artificial Intelligence (AI) research center in Brazzaville Congo, with focus on technology and innovationThe center,",
      "sourceUrl": null,
      "webUrl": "https://africa.cgtn.com/2022/02/24/first-ai-research-center-inaugurated-in-republic-of-congo/",
      "originalUrl": "https://www.msn.com/en-xl/africa/other/eca-to-inaugurate-africa-s-1st-ai-research-centre-in-brazzaville-congo/ar-AAUdZz8",
      "featuredContent": null,
      "highlight": null,
      "heat": 147,
      "tags": null,
      "images": [
        {
          "url": "https://africa.cgtn.com/wp-content/photo-gallery/2022/02/Advantages_and_Disadvantages_of_artificial_intelligence.jpg",
          "width": 848,
          "height": 477,
          "title": null,
          "attribution": null,
          "isCached": true
        }
      ],
      "content": "\r\n",
      "type": "article",
      "ampWebUrl": null,
      "cdnAmpWebUrl": null,
      "publishedDateTime": "2022-02-22T16:00:00-08:00",
      "updatedDateTime": null,
      "provider": {
        "name": "cgtn.com/2022/02/24/first-ai-research-center-inaugurated-in-republic-of-congo/",
        "domain": "cgtn.com/2022/02/24/first-ai-research-center-inaugurated-in-republic-of-congo/",
        "images": null,
        "publishers": null,
        "authors": null
      },
      "locale": "en-us",
      "categories": [
        "news"
      ],
      "topics": [
        "AI"
      ]
    },
    {
      "path": "_news/2022-02-23-educational-robotics-to-top-4-billion-by-2028.md",
      "title": "Educational Robotics to Top $4 Billion by 2028",
      "excerpt": "Educational Robotics to Top $4 Billion by 2028. By David Nagel; 02/23/22; The need for robotics in education will help drive double-digit annual growth",
      "sourceUrl": null,
      "webUrl": "https://thejournal.com/Articles/2022/02/23/Educational-Robotics-to-Top-4-Billion-by-2028.aspx?s=the_nu_240222&p=1",
      "originalUrl": "https://thejournal.com/Articles/2022/02/23/Educational-Robotics-to-Top-4-Billion-by-2028.aspx?s=the_nu_240222&p=1",
      "featuredContent": null,
      "highlight": null,
      "heat": null,
      "tags": null,
      "images": [
        {
          "url": "https://thejournal.com/~/media/EDU/THEJournal/THElogo.jpg",
          "width": 1200,
          "height": 630,
          "title": null,
          "attribution": null,
          "isCached": true
        }
      ],
      "content": "\r\n",
      "type": "article",
      "ampWebUrl": null,
      "cdnAmpWebUrl": null,
      "publishedDateTime": "2022-02-22T16:00:00-08:00",
      "updatedDateTime": null,
      "provider": {
        "name": "The Journal",
        "domain": "thejournal.com",
        "images": null,
        "publishers": null,
        "authors": null
      },
      "locale": "en-us",
      "categories": [
        "news"
      ],
      "topics": [
        "AI in Robotics",
        "AI"
      ]
    },
    {
      "path": "_news/2022-02-23-ai-player-wildwood-data-inc-guarantees-more-sales-for-small-businesses.md",
      "title": "AI Player Wildwood Data, Inc. Guarantees More Sales For Small Businesses",
      "excerpt": "Their guarantee is possible because of their access to both public and private data aggregates, their proprietary AI, and their acquisition approach. Their approaches and algorithms were beta tested using a handful of startup companies with memberships at ...",
      "sourceUrl": null,
      "webUrl": "https://www.benzinga.com/pressreleases/22/02/ab25769210/ai-player-wildwood-data-inc-guarantees-more-sales-for-small-businesses",
      "originalUrl": "https://www.benzinga.com/pressreleases/22/02/ab25769210/ai-player-wildwood-data-inc-guarantees-more-sales-for-small-businesses",
      "featuredContent": null,
      "highlight": null,
      "heat": 73,
      "tags": null,
      "images": [
        {
          "url": "https://www.benzinga.com/images/schema-image-default.png",
          "width": 1043,
          "height": 1043,
          "title": null,
          "attribution": null,
          "isCached": true
        }
      ],
      "content": "\r\n",
      "type": "article",
      "ampWebUrl": "https://www.benzinga.com/amp/content/25769210",
      "cdnAmpWebUrl": "https://www-benzinga-com.cdn.ampproject.org/c/s/www.benzinga.com/amp/content/25769210",
      "publishedDateTime": "2022-02-22T15:26:00-08:00",
      "updatedDateTime": null,
      "provider": {
        "name": "Benzinga.com",
        "domain": "benzinga.com",
        "images": null,
        "publishers": null,
        "authors": null
      },
      "locale": "en-us",
      "categories": [
        "news"
      ],
      "topics": [
        "AI",
        "AI in Sales"
      ]
    },
    {
      "path": "_news/2022-02-23-irs-offers-alternative-to-facial-recognition.md",
      "title": "IRS offers alternative to facial recognition",
      "excerpt": "A short-term option involves a virtual interview with IRS personnel to authenticate taxpayers’ and practitioners’ identities for online services.",
      "sourceUrl": null,
      "webUrl": "https://www.thetaxadviser.com/news/2022/feb/irs-offers-alternative-to-facial-recognition.html",
      "originalUrl": "https://www.thetaxadviser.com/news/2022/feb/irs-offers-alternative-to-facial-recognition.html",
      "featuredContent": null,
      "highlight": null,
      "heat": null,
      "tags": null,
      "images": [
        {
          "url": "https://www.thetaxadviser.com/content/dam/tta/tta-default-cover-image.jpg",
          "width": 255,
          "height": 335,
          "title": null,
          "attribution": null,
          "isCached": true
        }
      ],
      "content": "\r\n",
      "type": "article",
      "ampWebUrl": null,
      "cdnAmpWebUrl": null,
      "publishedDateTime": "2022-02-22T14:21:00-08:00",
      "updatedDateTime": null,
      "provider": {
        "name": "The Tax Adviser",
        "domain": "thetaxadviser.com",
        "images": null,
        "publishers": null,
        "authors": null
      },
      "locale": "en-us",
      "categories": [
        "news"
      ],
      "topics": [
        "Computer Vision",
        "AI"
      ]
    },
    {
      "path": "_news/2022-02-23-propelled-by-multiple-trends-alphabet-stock-should-rally.md",
      "title": "Propelled by Multiple Trends, Alphabet Stock Should Rally",
      "excerpt": "Finally, Alphabet is using advancements that it has made in artificial intelligence (AI ... I was very bullish on Waymo, writing that “There are multiple signs that […] Waymo is way ahead ...",
      "sourceUrl": null,
      "webUrl": "https://investorplace.com/2022/02/goog-stock-propelled-by-multiple-trends-alphabet-stock-should-rally/",
      "originalUrl": "https://investorplace.com/2022/02/goog-stock-propelled-by-multiple-trends-alphabet-stock-should-rally/",
      "featuredContent": null,
      "highlight": null,
      "heat": null,
      "tags": null,
      "images": [
        {
          "url": "https://investorplace.com/wp-content/uploads/2019/07/goog1600b.jpg",
          "width": 1600,
          "height": 900,
          "title": null,
          "attribution": null,
          "isCached": true
        }
      ],
      "content": "\r\n",
      "type": "article",
      "ampWebUrl": "https://investorplace.com/2022/02/goog-stock-propelled-by-multiple-trends-alphabet-stock-should-rally/amp/",
      "cdnAmpWebUrl": "https://investorplace-com.cdn.ampproject.org/c/s/investorplace.com/2022/02/goog-stock-propelled-by-multiple-trends-alphabet-stock-should-rally/amp/",
      "publishedDateTime": "2022-02-22T13:37:00-08:00",
      "updatedDateTime": null,
      "provider": {
        "name": "InvestorPlace",
        "domain": "investorplace.com",
        "images": null,
        "publishers": null,
        "authors": null
      },
      "locale": "en-us",
      "categories": [
        "news"
      ],
      "topics": [
        "AI in Autos",
        "AI"
      ]
    },
    {
      "path": "_news/2022-02-23-facial-recognition-technology-faces-mounting-legal-ethical-questions.md",
      "title": "Facial recognition technology faces mounting legal, ethical questions",
      "excerpt": "Facebook's parent company, Meta, is under scrutiny for its use of facial recognition technology from 2009 until late 2021. The Texas Attorney General, Ken Paxton, filed a lawsuit in mid-February, seeking damages related to Facebook's photo services.",
      "sourceUrl": null,
      "webUrl": "https://www.wcpo.com/news/national/facial-recognition-technology-faces-mounting-legal-ethical-questions",
      "originalUrl": "https://www.wcpo.com/news/national/facial-recognition-technology-faces-mounting-legal-ethical-questions",
      "featuredContent": null,
      "highlight": null,
      "heat": null,
      "tags": null,
      "images": [
        {
          "url": "https://ewscripps.brightspotcdn.com/dims4/default/cc0c13f/2147483647/strip/true/crop/702x395+69+0/resize/1280x720!/quality/90/?url=https%3A%2F%2Fewscripps.brightspotcdn.com%2Ff4%2F94%2Fd4d0abae4343a0b874f0fcaff0a7%2Fscreen-shot-2022-02-22-at-3.01.08%20PM.png",
          "width": 1280,
          "height": 720,
          "title": null,
          "attribution": null,
          "isCached": true
        }
      ],
      "content": "\r\n",
      "type": "article",
      "ampWebUrl": "https://www.wcpo.com/news/national/facial-recognition-technology-faces-mounting-legal-ethical-questions?_amp=true",
      "cdnAmpWebUrl": "https://www-wcpo-com.cdn.ampproject.org/c/s/www.wcpo.com/news/national/facial-recognition-technology-faces-mounting-legal-ethical-questions?_amp=true",
      "publishedDateTime": "2022-02-22T13:06:00-08:00",
      "updatedDateTime": null,
      "provider": {
        "name": "WCPO Cincinnati",
        "domain": "wcpo.com",
        "images": null,
        "publishers": null,
        "authors": null
      },
      "locale": "en-us",
      "categories": [
        "news"
      ],
      "topics": [
        "Computer Vision",
        "AI",
        "AI Ethics"
      ]
    },
    {
      "path": "_news/2022-02-23-irs-will-let-tax-payers-opt-out-of-facial-recognition-but-theres-a-big-catch.md",
      "title": "IRS will let tax payers opt out of facial recognition, but there's a big catch",
      "excerpt": "Although the IRS has dropped its plans to use video selfies to verify the identities of taxpayers, this year's tax season is still set to be a bit more chaotic than usual. Originally the government agency had planned to use the third-party identity verification provider ID.",
      "sourceUrl": null,
      "webUrl": "https://www.techradar.com/news/irs-will-let-tax-payers-opt-out-of-facial-recognition-but-theres-a-big-catch",
      "originalUrl": "https://www.techradar.com/news/irs-will-let-tax-payers-opt-out-of-facial-recognition-but-theres-a-big-catch",
      "featuredContent": null,
      "highlight": null,
      "heat": 105,
      "tags": null,
      "images": [
        {
          "url": "https://cdn.mos.cms.futurecdn.net/AhxWMLamn9z3RMdEzxGwYE-1200-80.jpg",
          "width": 970,
          "height": 545,
          "title": null,
          "attribution": null,
          "isCached": true
        }
      ],
      "content": "\r\n",
      "type": "article",
      "ampWebUrl": null,
      "cdnAmpWebUrl": null,
      "publishedDateTime": "2022-02-22T12:00:00-08:00",
      "updatedDateTime": null,
      "provider": {
        "name": "TechRadar",
        "domain": "techradar.com",
        "images": [
          {
            "url": "https://everyday-cc.github.io/ai/assets/images/organizations/techradar.com-50x50.jpg",
            "width": 50,
            "height": 50,
            "title": null,
            "attribution": null,
            "isCached": false
          }
        ],
        "publishers": null,
        "authors": null
      },
      "locale": "en-us",
      "categories": [
        "news"
      ],
      "topics": [
        "Computer Vision",
        "AI"
      ]
    },
    {
      "path": "_news/2022-02-23-tull-family-foundation-gifts-prep-school-20m-for-labs-robotics.md",
      "title": "Tull Family Foundation Gifts Prep School $20M for Labs, Robotics",
      "excerpt": "Sewickley Academy in Pittsburgh will use the donation for facilities, scholarships and STEM offerings such as adding cybersecurity, artificial intelligence and advanced robotics to its computer science department.",
      "sourceUrl": null,
      "webUrl": "https://www.govtech.com/education/k-12/tull-family-foundation-gifts-prep-school-20m-for-labs-robotics",
      "originalUrl": "https://www.govtech.com/education/k-12/tull-family-foundation-gifts-prep-school-20m-for-labs-robotics",
      "featuredContent": null,
      "highlight": null,
      "heat": 74,
      "tags": null,
      "images": [
        {
          "url": "https://erepublic.brightspotcdn.com/dims4/default/5ddf76b/2147483647/strip/true/crop/2048x1068+0+432/resize/840x438!/quality/90/?url=http%3A%2F%2Ferepublic-brightspot.s3.amazonaws.com%2Fd0%2F05%2F86c20d864ffdb8a6a71d21d4bca1%2Fsewickley-academy.jpg",
          "width": 840,
          "height": 438,
          "title": null,
          "attribution": null,
          "isCached": true
        }
      ],
      "content": "\r\n",
      "type": "article",
      "ampWebUrl": "https://www.govtech.com/education/k-12/tull-family-foundation-gifts-prep-school-20m-for-labs-robotics?_amp=true",
      "cdnAmpWebUrl": "https://www-govtech-com.cdn.ampproject.org/c/s/www.govtech.com/education/k-12/tull-family-foundation-gifts-prep-school-20m-for-labs-robotics?_amp=true",
      "publishedDateTime": "2022-02-22T11:43:00-08:00",
      "updatedDateTime": null,
      "provider": {
        "name": "Government Technology",
        "domain": "govtech.com",
        "images": null,
        "publishers": null,
        "authors": null
      },
      "locale": "en-us",
      "categories": [
        "news"
      ],
      "topics": [
        "AI in Robotics",
        "AI"
      ]
    },
    {
      "path": "_news/2022-02-22-an-intro-to-ai-made-for-students.md",
      "title": "An intro to AI, made for students",
      "excerpt": "Adorable, operatic blobs. A global, online guessing game. Scribbles that transform into works of art. These may not sound like they’re part of a curriculum, but learning the basics of how artificial intelligence (AI) works doesn’t have to be complicated, super-technical or boring.To celebrate Digital",
      "sourceUrl": null,
      "webUrl": "https://blog.google/technology/ai/discover-ai-in-daily-life/",
      "originalUrl": "https://blog.google/technology/ai/discover-ai-in-daily-life/",
      "featuredContent": null,
      "highlight": null,
      "heat": 149,
      "tags": null,
      "images": [
        {
          "url": "https://storage.googleapis.com/gweb-uniblog-publish-prod/images/StillForKeyword_1.max-1300x1300.png",
          "width": 1300,
          "height": 731,
          "title": null,
          "attribution": null,
          "isCached": true
        }
      ],
      "content": "\r\n",
      "type": "article",
      "ampWebUrl": "https://blog.google/technology/ai/discover-ai-in-daily-life/amp/",
      "cdnAmpWebUrl": "https://blog-google.cdn.ampproject.org/c/s/blog.google/technology/ai/discover-ai-in-daily-life/amp/",
      "publishedDateTime": "2022-02-22T11:00:00-08:00",
      "updatedDateTime": null,
      "provider": {
        "name": "Google",
        "domain": "blog.google",
        "images": [
          {
            "url": "https://everyday-cc.github.io/ai/assets/images/organizations/blog.google-50x50.jpg",
            "width": 50,
            "height": 50,
            "title": null,
            "attribution": null,
            "isCached": false
          }
        ],
        "publishers": null,
        "authors": null
      },
      "locale": "en-us",
      "categories": [
        "news"
      ],
      "topics": [
        "AI",
        "Google AI"
      ]
    },
    {
      "path": "_news/2022-02-23-artificial-intelligence-ai-future-of-neurosurgery.md",
      "title": "Artificial Intelligence (AI) — Future of Neurosurgery?",
      "excerpt": "Technical performance and learning outcomes during simulated brain tumor removal may be enhanced by artificial intelligence (AI) as per a study at the Neurosurgical Simulation and Artificial Intelligence Learning Centre at The Neuro (Montreal Neurological ...",
      "sourceUrl": null,
      "webUrl": "https://www.medindia.net/news/artificial-intelligence-ai-future-of-neurosurgery-205768-1.htm",
      "originalUrl": "https://www.medindia.net/news/artificial-intelligence-ai-future-of-neurosurgery-205768-1.htm",
      "featuredContent": null,
      "highlight": null,
      "heat": 72,
      "tags": null,
      "images": [
        {
          "url": "https://images.medindia.net/amp-images/health-images/artificial-intelligence-provides-clearer-mir-scans.jpg",
          "width": 1200,
          "height": 1000,
          "title": null,
          "attribution": null,
          "isCached": true
        }
      ],
      "content": "\r\n",
      "type": "article",
      "ampWebUrl": "https://www.medindia.net/amp/news/artificial-intelligence-ai-future-of-neurosurgery-205768-1.htm",
      "cdnAmpWebUrl": "https://www-medindia-net.cdn.ampproject.org/c/s/www.medindia.net/amp/news/artificial-intelligence-ai-future-of-neurosurgery-205768-1.htm",
      "publishedDateTime": "2022-02-22T10:26:00-08:00",
      "updatedDateTime": null,
      "provider": {
        "name": "Medindia",
        "domain": "medindia.net",
        "images": null,
        "publishers": null,
        "authors": null
      },
      "locale": "en-us",
      "categories": [
        "news"
      ],
      "topics": [
        "AI"
      ]
    },
    {
      "path": "_news/2022-02-23-machine-learning-and-artificial-intelligence-a-futuristic-approach-to-employee-engagement.md",
      "title": "Machine learning and Artificial Intelligence: A futuristic approach to employee engagement",
      "excerpt": "The subsequent sections bring to light the modern techniques to engage employees. Machine Learning (ML) and Artificial Intelligence (AI) – The New-Age Employee Engagement Tools New-age digital ...",
      "sourceUrl": null,
      "webUrl": "https://timesofindia.indiatimes.com/blogs/voices/machine-learning-and-artificial-intelligence-a-futuristic-approach-to-employee-engagement/",
      "originalUrl": "https://timesofindia.indiatimes.com/blogs/voices/machine-learning-and-artificial-intelligence-a-futuristic-approach-to-employee-engagement/",
      "featuredContent": null,
      "highlight": null,
      "heat": 74,
      "tags": null,
      "images": [
        {
          "url": "https://static.toiimg.com/photo/75433510.cms",
          "width": 330,
          "height": 300,
          "title": null,
          "attribution": null,
          "isCached": true
        }
      ],
      "content": "\r\n",
      "type": "article",
      "ampWebUrl": "https://timesofindia.indiatimes.com/blogs/voices/machine-learning-and-artificial-intelligence-a-futuristic-approach-to-employee-engagement/",
      "cdnAmpWebUrl": "https://timesofindia-indiatimes-com.cdn.ampproject.org/c/s/timesofindia.indiatimes.com/blogs/voices/machine-learning-and-artificial-intelligence-a-futuristic-approach-to-employee-engagement/",
      "publishedDateTime": "2022-02-22T10:04:00-08:00",
      "updatedDateTime": null,
      "provider": {
        "name": "India Times",
        "domain": "indiatimes.com",
        "images": null,
        "publishers": null,
        "authors": null
      },
      "locale": "en-us",
      "categories": [
        "news"
      ],
      "topics": [
        "Machine Learning",
        "AI"
      ]
    }
  ],
  "nextPage": 57
}